Workbook

Sheet README
A1: Lumina Baby & Family Care Ltd — Commercial Finance — Pricing, Margin & Customer Profitability
A3: Project 2 | Commercial Finance flagship case study | V1
A5: Business problem
A6: Commercial Finance needs to identify which customers, channels and SKUs create profitable growth after discounts, COGS, freight and promotional spend. This project uses a SQL-first data pipeline and Excel reporting layer to answer that question.
A12: V1 build
A13: Data model | B13: Star schema: Fact Sales + Date/Product/Customer dimensions
A14: SQL | B14: SQLite database and reusable commercial-finance queries
A15: Customer profitability | B15: Net revenue, discount, GP, cost-to-serve, contribution
A16: Product profitability | B16: SKU, brand and category economics
A17: Channel analysis | B17: Route-to-market contribution and margin
A18: Monthly trend | B18: Revenue, discount, promo spend and margin
A19: Dashboard | B19: Commercial Finance KPI summary and charts
A20: Power BI prep | B20: CSV star schema + DAX measure library
A21: Data volume | B21: 2,000 synthetic transactions | 48 SKUs | 90 customers
A23: Portfolio integrity
A24: All company, customer, product and transaction data is synthetic. Present outputs as simulated/modelled findings, not realised employer results.
A40: V2 — Commercial Decision Layer
A41: V2 adds discount-leakage and repricing analysis, customer profitability quadrants, a pricing waterfall, promotion-effectiveness ROI proxies, customer-concentration / Pareto analysis, SKU rationalisation, Jan–Sep Price–Volume–Mix analysis and a quantified Commercial Finance action plan. The aim is to move from reporting revenue and margin to recommending pricing, customer, promotion and portfolio actions.
A50: V3 — Commercial Management Layer
A51: V3 adds a risk-adjusted customer repricing scenario model, an accountable customer action register, formula-driven Commercial Finance commentary, an executive management pack and a Power BI build specification. The repricing model explicitly balances discount recovery against volume-retention risk so that modelled upside is presented as a planning scenario rather than a guaranteed saving.
A60: Final Portfolio Release
A61: Final release prepared for CV, LinkedIn and interview use. The release package includes the final workbook, SQLite database, SQL queries, source CSVs, recruiter-facing screenshots, CV bullets, LinkedIn launch copy and interview explanations. Power BI is described only as a build specification because no PBIX file is included. All pricing opportunities are modelled scenarios, not realised savings.

Sheet Assumptions
A1: Commercial Assumptions
A3: Channel | B3: Typical Discount Range | C3: Freight % Net Revenue | D3: Source
A4: Grocery | B4: 9% – 16% | C4: 0.018 | D4: Synthetic assumption
A5: Pharmacy | B5: 7% – 13% | C5: 0.021 | D5: Synthetic assumption
A6: Online Marketplace | B6: 10% – 18% | C6: 0.026 | D6: Synthetic assumption
A7: DTC | B7: 2% – 8% | C7: 0.045 | D7: Synthetic assumption
A8: Wholesale | B8: 13% – 21% | C8: 0.015 | D8: Synthetic assumption
A9: Baby Specialist | B9: 6% – 12% | C9: 0.023 | D9: Synthetic assumption
A12: Portfolio Assumption | B12: Value
A13: 2026 price inflation | B13: 0.035
A14: 2026 unit-cost inflation | B14: 0.045
A15: Strategic discount premium | B15: 0.025
A16: Promotional discount increment | B16: 0.035
A17: Transaction lines | B17: 2000
A21: V2 Pricing Governance Assumptions
A22: Channel | B22: Target Base Discount | C22: Source
A23: Grocery | B23: 0.12 | C23: Synthetic pricing-policy assumption
A24: Pharmacy | B24: 0.1 | C24: Synthetic pricing-policy assumption
A25: Online Marketplace | B25: 0.14 | C25: Synthetic pricing-policy assumption
A26: DTC | B26: 0.05 | C26: Synthetic pricing-policy assumption
A27: Wholesale | B27: 0.16 | C27: Synthetic pricing-policy assumption
A28: Baby Specialist | B28: 0.09 | C28: Synthetic pricing-policy assumption
A30: V2 Customer / Promotion Policy
A31: Strategic tier premium | B31: 0.02
A32: Core tier premium | B32: 0.01
A33: Long-tail tier premium | B33: 0
A34: Promo-policy increment × promo sales share | B34: 0.02
A35: Potential leakage recapture factor | B35: 0.7

Sheet Data Model
A1: Power BI / SQL Star Schema
A3: Model relationships
A4: Table | B4: Primary Key | C4: Relationship | D4: Fact Key | E4: Grain | F4: Rows | G4: Purpose | H4: Source
A5: Dim Date | B5: Date | C5: 1 → many | D5: Fact Sales.Date | E5: 1 row per calendar day | F5: 638 | G5: Time intelligence | H5: Synthetic
A6: Dim Product | B6: Product_ID | C6: 1 → many | D6: Fact Sales.Product_ID | E6: 1 row per SKU | F6: 48 | G6: Product hierarchy | H6: Synthetic
A7: Dim Customer | B7: Customer_ID | C7: 1 → many | D7: Fact Sales.Customer_ID | E7: 1 row per customer | F7: 90 | G7: Customer/channel hierarchy | H7: Synthetic
A8: Fact Sales | B8: Transaction_ID | C8: many side | D8: — | E8: 1 transaction line | F8: 2000 | G8: Commercial economics | H8: Synthetic ERP/CRM extract

Sheet Dim Product
A1: Product Dimension
A3: Product_ID | B3: Brand | C3: Category | D3: SKU_Name | E3: Pack_Size | F3: Base_List_Price (£) | G3: Standard_Unit_Cost (£) | H3: Launch_Status | I3: Source
A4: P001 | B4: Nurtura | C4: Diapers | D4: Nurtura Diapers 24 pack | E4: 24 pack | F4: 10.5 | G4: 5.55 | H4: Core | I4: Synthetic portfolio master data
A5: P002 | B5: Nurtura | C5: Diapers | D5: Nurtura Diapers 40 pack | E5: 40 pack | F5: 16.28 | G5: 8.58 | H5: Core | I5: Synthetic portfolio master data
A6: P003 | B6: Nurtura | C6: Wipes | D6: Nurtura Wipes 4 pack | E6: 4 pack | F6: 5.2 | G6: 2.74 | H6: Core | I6: Synthetic portfolio master data
A7: P004 | B7: Nurtura | C7: Wipes | D7: Nurtura Wipes 8 pack | E7: 8 pack | F7: 8.06 | G7: 4.06 | H7: Core | I7: Synthetic portfolio master data
A8: P005 | B8: Nurtura | C8: Baby Bath | D8: Nurtura Baby Bath 250ml | E8: 250ml | F8: 4.8 | G8: 2.29 | H8: Core | I8: Synthetic portfolio master data
A9: P006 | B9: Nurtura | C9: Baby Bath | D9: Nurtura Baby Bath 500ml | E9: 500ml | F9: 7.44 | G9: 3.6 | H9: Core | I9: Synthetic portfolio master data
A10: P007 | B10: Nurtura | C10: Skincare | D10: Nurtura Skincare 100ml | E10: 100ml | F10: 6.4 | G10: 2.99 | H10: Growth | I10: Synthetic portfolio master data
A11: P008 | B11: Nurtura | C11: Skincare | D11: Nurtura Skincare 200ml | E11: 200ml | F11: 9.92 | G11: 4.57 | H11: Core | I11: Synthetic portfolio master data
A12: P009 | B12: Nurtura | C12: Feeding | D12: Nurtura Feeding 2 pack | E12: 2 pack | F12: 8.2 | G12: 4.03 | H12: Core | I12: Synthetic portfolio master data
A13: P010 | B13: Nurtura | C13: Feeding | D13: Nurtura Feeding 4 pack | E13: 4 pack | F13: 8.2 | G13: 4.14 | H13: Core | I13: Synthetic portfolio master data
A14: P011 | B14: Nurtura | C14: Nursery | D14: Nurtura Nursery Single | E14: Single | F14: 14.5 | G14: 8.03 | H14: Core | I14: Synthetic portfolio master data
A15: P012 | B15: Nurtura | C15: Nursery | D15: Nurtura Nursery Twin pack | E15: Twin pack | F15: 22.48 | G15: 12.47 | H15: Core | I15: Synthetic portfolio master data
... A51: P048 | B51: TinySteps | C51: Nursery | D51: TinySteps Nursery Twin pack | E51: Twin pack | F51: 20.23 | G51: 11.65 | H51: Core | I51: Synthetic portfolio master data

Sheet Dim Customer
A1: Customer Dimension
A3: Customer_ID | B3: Customer_Name | C3: Channel | D3: Region | E3: Tier | F3: Payment_Terms_Days | G3: Account_Status | H3: Source
A4: C001 | B4: Northgate Grocers 01 | C4: Grocery | D4: North | E4: Strategic | F4: 45 | G4: Active | H4: Synthetic portfolio master data
A5: C002 | B5: Northgate Grocers 02 | C5: Grocery | D5: Wales | E5: Strategic | F5: 45 | G5: Active | H5: Synthetic portfolio master data
A6: C003 | B6: Northgate Grocers 03 | C6: Grocery | D6: London & South East | E6: Strategic | F6: 45 | G6: Active | H6: Synthetic portfolio master data
A7: C004 | B7: Northgate Grocers 04 | C7: Grocery | D7: North | E7: Core | F7: 30 | G7: Active | H7: Synthetic portfolio master data
A8: C005 | B8: Northgate Grocers 05 | C8: Grocery | D8: Wales | E8: Core | F8: 30 | G8: Active | H8: Synthetic portfolio master data
A9: C006 | B9: Northgate Grocers 06 | C9: Grocery | D9: London & South East | E9: Core | F9: 30 | G9: Active | H9: Synthetic portfolio master data
A10: C007 | B10: Northgate Grocers 07 | C10: Grocery | D10: North | E10: Core | F10: 30 | G10: Active | H10: Synthetic portfolio master data
A11: C008 | B11: Northgate Grocers 08 | C11: Grocery | D11: Wales | E11: Core | F11: 30 | G11: Active | H11: Synthetic portfolio master data
A12: C009 | B12: Northgate Grocers 09 | C12: Grocery | D12: London & South East | E12: Core | F12: 30 | G12: Active | H12: Synthetic portfolio master data
A13: C010 | B13: Northgate Grocers 10 | C13: Grocery | D13: North | E13: Long Tail | F13: 21 | G13: Active | H13: Synthetic portfolio master data
A14: C011 | B14: Northgate Grocers 11 | C14: Grocery | D14: Wales | E14: Long Tail | F14: 21 | G14: Active | H14: Synthetic portfolio master data
A15: C012 | B15: Northgate Grocers 12 | C15: Grocery | D15: London & South East | E15: Long Tail | F15: 21 | G15: Active | H15: Synthetic portfolio master data
... A93: C090 | B93: LittleNest Retail 15 | C93: Baby Specialist | D93: Scotland | E93: Long Tail | F93: 21 | G93: Active | H93: Synthetic portfolio master data

Sheet Dim Date
A1: Date Dimension
A3: Date | B3: Year | C3: Quarter | D3: Month_No | E3: Month | F3: Year_Month | G3: Weekday
A4: 45658 | B4: 2025 | C4: Q1 | D4: 1 | E4: Jan | F4: 2025-01 | G4: Wednesday
A5: 45659 | B5: 2025 | C5: Q1 | D5: 1 | E5: Jan | F5: 2025-01 | G5: Thursday
A6: 45660 | B6: 2025 | C6: Q1 | D6: 1 | E6: Jan | F6: 2025-01 | G6: Friday
A7: 45661 | B7: 2025 | C7: Q1 | D7: 1 | E7: Jan | F7: 2025-01 | G7: Saturday
A8: 45662 | B8: 2025 | C8: Q1 | D8: 1 | E8: Jan | F8: 2025-01 | G8: Sunday
A9: 45663 | B9: 2025 | C9: Q1 | D9: 1 | E9: Jan | F9: 2025-01 | G9: Monday
A10: 45664 | B10: 2025 | C10: Q1 | D10: 1 | E10: Jan | F10: 2025-01 | G10: Tuesday
A11: 45665 | B11: 2025 | C11: Q1 | D11: 1 | E11: Jan | F11: 2025-01 | G11: Wednesday
A12: 45666 | B12: 2025 | C12: Q1 | D12: 1 | E12: Jan | F12: 2025-01 | G12: Thursday
A13: 45667 | B13: 2025 | C13: Q1 | D13: 1 | E13: Jan | F13: 2025-01 | G13: Friday
A14: 45668 | B14: 2025 | C14: Q1 | D14: 1 | E14: Jan | F14: 2025-01 | G14: Saturday
A15: 45669 | B15: 2025 | C15: Q1 | D15: 1 | E15: Jan | F15: 2025-01 | G15: Sunday
... A641: 46295 | B641: 2026 | C641: Q3 | D641: 9 | E641: Sep | F641: 2026-09 | G641: Wednesday

Sheet Fact Sales
A1: Fact Sales — SQL / Power BI Source Table
A3: Transaction_ID | B3: Date | C3: Customer_ID | D3: Product_ID | E3: Channel | F3: Region | G3: Customer_Tier | H3: Units | I3: List_Price | J3: Gross_Sales | K3: Discount_Pct | L3: Discount_Value | M3: Net_Revenue | N3: Unit_COGS | O3: COGS | P3: Gross_Profit | Q3: GP_Pct | R3: Freight_Rate | S3: Freight | T3: Promo_Spend | U3: Contribution_Profit | V3: Contribution_Margin | W3: Promo_Flag | X3: Source
A4: T000001 | B4: 46245 | C4: C077 | D4: P008 | E4: Baby Specialist | F4: Midlands | G4: Strategic | H4: 6 | I4: 10.28 | J4: 61.68 | K4: 0.13585923 | L4: 8.3797972 | M4: 53.300203 | N4: 4.78 | O4: 28.68 | P4: 24.620203 | Q4: 0.46191574 | R4: 0.023 | S4: 1.2259047 | T4: 0 | U4: 23.394298 | V4: 0.43891574 | W4: Non-Promo | X4: Synthetic ERP/CRM extract
A5: T000002 | B5: 45847 | C5: C078 | D5: P029 | E5: Baby Specialist | F5: Scotland | G5: Strategic | H5: 39 | I5: 5.11 | J5: 199.29 | K5: 0.12226316 | L5: 24.365826 | M5: 174.92417 | N5: 2.21 | O5: 86.19 | P5: 88.734174 | Q5: 0.50727222 | R5: 0.023 | S5: 4.023256 | T5: 4.02 | U5: 80.690918 | V5: 0.46129083 | W5: Promo | X5: Synthetic ERP/CRM extract
A6: T000003 | B6: 45788 | C6: C020 | D6: P025 | E6: Pharmacy | F6: Midlands | G6: Core | H6: 38 | I6: 11.48 | J6: 436.24 | K6: 0.13279986 | L6: 57.932612 | M6: 378.30739 | N6: 5.45 | O6: 207.1 | P6: 171.20739 | Q6: 0.45256158 | R6: 0.021 | S6: 7.9444551 | T6: 0 | U6: 163.26293 | V6: 0.43156158 | W6: Non-Promo | X6: Synthetic ERP/CRM extract
A7: T000004 | B7: 46107 | C7: C016 | D7: P028 | E7: Pharmacy | F7: Northern Ireland | G7: Strategic | H7: 40 | I7: 8.94 | J7: 357.6 | K7: 0.13896154 | L7: 49.692648 | M7: 307.90735 | N7: 4.44 | O7: 177.6 | P7: 130.30735 | Q7: 0.42320312 | R7: 0.021 | S7: 6.4660544 | T7: 0 | U7: 123.8413 | V7: 0.40220312 | W7: Non-Promo | X7: Synthetic ERP/CRM extract
A8: T000005 | B8: 46011 | C8: C074 | D8: P017 | E8: Wholesale | F8: Wales | G8: Long Tail | H8: 4 | I8: 4.55 | J8: 18.2 | K8: 0.19827505 | L8: 3.608606 | M8: 14.591394 | N8: 2.18 | O8: 8.72 | P8: 5.871394 | Q8: 0.40238746 | R8: 0.015 | S8: 0.21887091 | T8: 0 | U8: 5.6525231 | V8: 0.38738746 | W8: Non-Promo | X8: Synthetic ERP/CRM extract
A9: T000006 | B9: 46237 | C9: C018 | D9: P039 | E9: Pharmacy | F9: Scotland | G9: Strategic | H9: 119 | I9: 4.89 | J9: 581.91 | K9: 0.15588672 | L9: 90.712043 | M9: 491.19796 | N9: 2.72 | O9: 323.68 | P9: 167.51796 | Q9: 0.3410396 | R9: 0.021 | S9: 10.315157 | T9: 6.13 | U9: 151.0728 | V9: 0.30755991 | W9: Promo | X9: Synthetic ERP/CRM extract
A10: T000007 | B10: 46230 | C10: C084 | D10: P001 | E10: Baby Specialist | F10: Scotland | G10: Core | H10: 93 | I10: 10.81 | J10: 1005.33 | K10: 0.12304343 | L10: 123.69925 | M10: 881.63075 | N10: 5.77 | O10: 536.61 | P10: 345.02075 | Q10: 0.39134383 | R10: 0.023 | S10: 20.277507 | T10: 0 | U10: 324.74324 | V10: 0.36834383 | W10: Non-Promo | X10: Synthetic ERP/CRM extract
A11: T000008 | B11: 45816 | C11: C035 | D11: P015 | E11: Online Marketplace | F11: Wales | G11: Core | H11: 75 | I11: 5 | J11: 375 | K11: 0.13925785 | L11: 52.221695 | M11: 322.7783 | N11: 2.78 | O11: 208.5 | P11: 114.2783 | Q11: 0.3540458 | R11: 0.026 | S11: 8.3922359 | T11: 0 | U11: 105.88607 | V11: 0.3280458 | W11: Non-Promo | X11: Synthetic ERP/CRM extract
A12: T000009 | B12: 46045 | C12: C037 | D12: P043 | E12: Online Marketplace | F12: North | G12: Core | H12: 4 | I12: 6.01 | J12: 24.04 | K12: 0.16307852 | L12: 3.9204077 | M12: 20.119592 | N12: 3.03 | O12: 12.12 | P12: 7.9995923 | Q12: 0.39760211 | R12: 0.026 | S12: 0.5231094 | T12: 0 | U12: 7.4764829 | V12: 0.37160211 | W12: Non-Promo | X12: Synthetic ERP/CRM extract
A13: T000010 | B13: 46264 | C13: C022 | D13: P023 | E13: Pharmacy | F13: Northern Ireland | G13: Core | H13: 4 | I13: 14.31 | J13: 57.24 | K13: 0.11831834 | L13: 6.7725421 | M13: 50.467458 | N13: 7.87 | O13: 31.48 | P13: 18.987458 | Q13: 0.37623171 | R13: 0.021 | S13: 1.0598166 | T13: 0 | U13: 17.927641 | V13: 0.35523171 | W13: Non-Promo | X13: Synthetic ERP/CRM extract
A14: T000011 | B14: 46059 | C14: C079 | D14: P025 | E14: Baby Specialist | F14: Northern Ireland | G14: Core | H14: 22 | I14: 11.84 | J14: 260.48 | K14: 0.15968023 | L14: 41.593505 | M14: 218.88649 | N14: 5.77 | O14: 126.94 | P14: 91.946495 | Q14: 0.42006472 | R14: 0.023 | S14: 5.0343894 | T14: 3.17 | U14: 83.742105 | V14: 0.38258233 | W14: Promo | X14: Synthetic ERP/CRM extract
A15: T000012 | B15: 45984 | C15: C039 | D15: P032 | E15: Online Marketplace | F15: London & South East | G15: Core | H15: 27 | I15: 10.69 | J15: 288.63 | K15: 0.13080742 | L15: 37.754946 | M15: 250.87505 | N15: 4.49 | O15: 121.23 | P15: 129.64505 | Q15: 0.5167714 | R15: 0.026 | S15: 6.5227514 | T15: 0 | U15: 123.1223 | V15: 0.4907714 | W15: Non-Promo | X15: Synthetic ERP/CRM extract
... A2003: T002000 | B2003: 45722 | C2003: C054 | D2003: P028 | E2003: DTC | F2003: Scotland | G2003: Core | H2003: 103 | I2003: 8.64 | J2003: 889.92 | K2003: 0.11224057 | L2003: 99.885126 | M2003: 790.03487 | N2003: 4.27 | O2003: 439.81 | P2003: 350.22487 | Q2003: 0.44330306 | R2003: 0.045 | S2003: 35.551569 | T2003: 21.32 | U2003: 293.3533 | V2003: 0.37131691 | W2003: Promo | X2003: Synthetic ERP/CRM extract

Sheet Customer Profitability
A1: Customer Profitability — SQL Analysis
A2: Source: commercial_finance_analysis.sql / commercial_finance.db
A3: Customer_ID | B3: Customer_Name | C3: Channel | D3: Tier | E3: Net_Revenue | F3: Discount_Value | G3: Discount_Rate | H3: Gross_Profit | I3: GP_Margin | J3: Cost_to_Serve | K3: Contribution_Profit | L3: Contribution_Margin
A4: C046 | B4: Direct Family Customer 01 | C4: DTC | D4: Strategic | E4: 29695.55 | F4: 2373.27 | G4: 0.074 | H4: 13186.69 | I4: 0.4441 | J4: 1376.16 | K4: 11810.53 | L4: 0.3977
A5: C047 | B5: Direct Family Customer 02 | C5: DTC | D5: Strategic | E5: 28448 | F5: 2530.95 | G5: 0.0817 | H5: 12079.36 | I5: 0.4246 | J5: 1326.48 | K5: 10752.88 | L5: 0.378
A6: C077 | B6: LittleNest Retail 02 | C6: Baby Specialist | D6: Strategic | E6: 23824.36 | F6: 3359.4 | G6: 0.1236 | H6: 9469.62 | I6: 0.3975 | J6: 673.37 | K6: 8796.25 | L6: 0.3692
A7: C001 | B7: Northgate Grocers 01 | C7: Grocery | D7: Strategic | E7: 23314.54 | F7: 4596.2 | G7: 0.1647 | H7: 8771.86 | I7: 0.3762 | J7: 538.59 | K7: 8233.27 | L7: 0.3531
A8: C048 | B8: Direct Family Customer 03 | C8: DTC | D8: Strategic | E8: 20694.21 | F8: 1891.79 | G8: 0.0838 | H8: 9143.6 | I8: 0.4418 | J8: 1068.38 | K8: 8075.22 | L8: 0.3902
A9: C018 | B9: WellSpring Pharmacy 03 | C9: Pharmacy | D9: Strategic | E9: 20045.68 | F9: 3146.25 | G9: 0.1357 | H9: 8185.65 | I9: 0.4083 | J9: 519.51 | K9: 7666.14 | L9: 0.3824
A10: C078 | B10: LittleNest Retail 03 | C10: Baby Specialist | D10: Strategic | E10: 19839.5 | F10: 2585.81 | G10: 0.1153 | H10: 7949.65 | I10: 0.4007 | J10: 496.64 | K10: 7453.01 | L10: 0.3757
A11: C031 | B11: HomeCart Online 01 | C11: Online Marketplace | D11: Strategic | E11: 21393.98 | F11: 4485.42 | G11: 0.1733 | H11: 8060.27 | I11: 0.3768 | J11: 761.83 | K11: 7298.43 | L11: 0.3411
A12: C017 | B12: WellSpring Pharmacy 02 | C12: Pharmacy | D12: Strategic | E12: 19566.79 | F12: 2828.5 | G12: 0.1263 | H12: 7588.89 | I12: 0.3878 | J12: 435.84 | K12: 7153.05 | L12: 0.3656
A13: C032 | B13: HomeCart Online 02 | C13: Online Marketplace | D13: Strategic | E13: 20627.81 | F13: 4282.95 | G13: 0.1719 | H13: 7451.06 | I13: 0.3612 | J13: 616.4 | K13: 6834.65 | L13: 0.3313
A14: C016 | B14: WellSpring Pharmacy 01 | C14: Pharmacy | D14: Strategic | E14: 17060.87 | F14: 2566.29 | G14: 0.1308 | H14: 7131.68 | I14: 0.418 | J14: 408.83 | K14: 6722.85 | L14: 0.3941
A15: C033 | B15: HomeCart Online 03 | C15: Online Marketplace | D15: Strategic | E15: 21060.26 | F15: 4610.84 | G15: 0.1796 | H15: 7309.75 | I15: 0.3471 | J15: 659.78 | K15: 6649.98 | L15: 0.3158
... A93: C045 | B93: HomeCart Online 15 | C93: Online Marketplace | D93: Long Tail | E93: 469.64 | F93: 73.89 | G93: 0.1359 | H93: 156.06 | I93: 0.3323 | J93: 12.21 | K93: 143.85 | L93: 0.3063

Sheet Product Profitability
A1: Product / SKU Profitability — SQL Analysis
A2: Source: commercial_finance_analysis.sql / commercial_finance.db
A3: Product_ID | B3: SKU_Name | C3: Brand | D3: Category | E3: Net_Revenue | F3: Units | G3: ASP | H3: Gross_Profit | I3: GP_Margin | J3: Promo_Spend | K3: Contribution_Profit | L3: Contribution_Margin
A4: P026 | B4: PureNest Diapers 40 pack | C4: PureNest | D4: Diapers | E4: 53279.74 | F4: 3466 | G4: 15.37 | H4: 23087.21 | I4: 0.4333 | J4: 103.59 | K4: 21637.14 | L4: 0.4061
A5: P014 | B5: LittleBloom Diapers 40 pack | C5: LittleBloom | D5: Diapers | E5: 46531.07 | F5: 3428 | G5: 13.57 | H5: 16855.56 | I5: 0.3622 | J5: 132.99 | K5: 15517.58 | L5: 0.3335
A6: P028 | B6: PureNest Wipes 8 pack | C6: PureNest | D6: Wipes | E6: 34065.07 | F6: 4431 | G6: 7.69 | H6: 14878.13 | I6: 0.4368 | J6: 194.05 | K6: 13760.7 | L6: 0.404
A7: P025 | B7: PureNest Diapers 24 pack | C7: PureNest | D7: Diapers | E7: 34328.82 | F7: 3487 | G7: 9.84 | H7: 14525.29 | I7: 0.4231 | J7: 165.8 | K7: 13533.55 | L7: 0.3942
A8: P002 | B8: Nurtura Diapers 40 pack | C8: Nurtura | D8: Diapers | E8: 36042.26 | F8: 2488 | G8: 14.49 | H8: 14229.28 | I8: 0.3948 | J8: 78.52 | K8: 13101.81 | L8: 0.3635
A9: P001 | B9: Nurtura Diapers 24 pack | C9: Nurtura | D9: Diapers | E9: 35430.98 | F9: 3864 | G9: 9.17 | H9: 13615.88 | I9: 0.3843 | J9: 88.11 | K9: 12637.6 | L9: 0.3567
A10: P038 | B10: TinySteps Diapers 40 pack | C10: TinySteps | D10: Diapers | E10: 37222.21 | F10: 2874 | G10: 12.95 | H10: 10430.42 | I10: 0.2802 | J10: 99.74 | K10: 9465.25 | L10: 0.2543
A11: P037 | B11: TinySteps Diapers 24 pack | C11: TinySteps | D11: Diapers | E11: 29819.92 | F11: 3574 | G11: 8.34 | H11: 9626.87 | I11: 0.3228 | J11: 159.65 | K11: 8651.13 | L11: 0.2901
A12: P004 | B12: Nurtura Wipes 8 pack | C12: Nurtura | D12: Wipes | E12: 21286.1 | F12: 3057 | G12: 6.96 | H12: 8539.65 | I12: 0.4012 | J12: 111.79 | K12: 7956.89 | L12: 0.3738
A13: P013 | B13: LittleBloom Diapers 24 pack | C13: LittleBloom | D13: Diapers | E13: 25714.65 | F13: 2908 | G13: 8.84 | H13: 8349.22 | I13: 0.3247 | J13: 99.21 | K13: 7615.22 | L13: 0.2961
A14: P030 | B14: PureNest Baby Bath 500ml | C14: PureNest | D14: Baby Bath | E14: 14568.73 | F14: 2041 | G14: 7.14 | H14: 7306.46 | I14: 0.5015 | J14: 56.18 | K14: 6855.49 | L14: 0.4706
A15: P003 | B15: Nurtura Wipes 4 pack | C15: Nurtura | D15: Wipes | E15: 17000.32 | F15: 3687 | G15: 4.61 | H15: 6676.91 | I15: 0.3928 | J15: 18.68 | K15: 6205.39 | L15: 0.365
... A51: P023 | B51: LittleBloom Nursery Single | C51: LittleBloom | D51: Nursery | E51: 1706.82 | F51: 138 | G51: 12.37 | H51: 656.51 | I51: 0.3846 | J51: 0 | K51: 599.86 | L51: 0.3515

Sheet Channel Analysis
A1: Channel Commercial Performance — SQL Analysis
A2: Source: commercial_finance_analysis.sql / commercial_finance.db
A3: Channel | B3: Net_Revenue | C3: Gross_Profit | D3: GP_Margin | E3: Discount_Value | F3: Discount_Rate | G3: Freight | H3: Promo_Spend | I3: Contribution_Profit | J3: Contribution_Margin
A4: DTC | B4: 128367.88 | C4: 56279.12 | D4: 0.4384 | E4: 10161.52 | F4: 0.0734 | G4: 5776.55 | H4: 342.25 | I4: 50160.32 | J4: 0.3908
A5: Baby Specialist | B5: 107222.88 | C5: 43215.94 | D5: 0.403 | E5: 13422.03 | F5: 0.1113 | G5: 2466.13 | H5: 322.29 | I5: 40427.52 | J5: 0.377
A6: Pharmacy | B6: 105922.65 | C6: 42866.38 | D6: 0.4047 | E6: 14666.02 | F6: 0.1216 | G6: 2224.38 | H6: 274.8 | I6: 40367.2 | J6: 0.3811
A7: Online Marketplace | B7: 105031.64 | C7: 38768.25 | D7: 0.3691 | E7: 21202.02 | F7: 0.168 | G7: 2730.82 | H7: 625.63 | I7: 35411.8 | J7: 0.3372
A8: Wholesale | B8: 97328.96 | C8: 34525.81 | D8: 0.3547 | E8: 22874.1 | F8: 0.1903 | G8: 1459.93 | H8: 247.65 | I8: 32818.23 | J8: 0.3372
A9: Grocery | B9: 88907.46 | C9: 33881.58 | D9: 0.3811 | E9: 15722.4 | F9: 0.1503 | G9: 1600.33 | H9: 402.51 | I9: 31878.73 | J9: 0.3586

Sheet Category Analysis
A1: Category Profitability — SQL Analysis
A2: Source: commercial_finance_analysis.sql / commercial_finance.db
A3: Category | B3: Net_Revenue | C3: Gross_Profit | D3: GP_Margin | E3: Contribution_Profit | F3: Contribution_Margin
A4: Diapers | B4: 298369.65 | C4: 110719.73 | D4: 0.3711 | E4: 102159.29 | F4: 0.3424
A5: Wipes | B5: 143676.81 | C5: 56197.4 | D5: 0.3911 | E5: 51973.18 | F5: 0.3617
A6: Baby Bath | B6: 62975.51 | C6: 28598.19 | D6: 0.4541 | E6: 26609.47 | F6: 0.4225
A7: Skincare | B7: 57161.69 | C7: 26389.12 | D7: 0.4617 | E7: 24612.23 | F7: 0.4306
A8: Feeding | B8: 42507.21 | C8: 17466.87 | D8: 0.4109 | E8: 16294.99 | F8: 0.3833
A9: Nursery | B9: 28090.59 | C9: 10165.76 | D9: 0.3619 | E9: 9414.64 | F9: 0.3352

Sheet Monthly Trend
A1: Monthly Commercial Trend — SQL Analysis
A2: Source: commercial_finance_analysis.sql / commercial_finance.db
A3: Year_Month | B3: Net_Revenue | C3: Gross_Profit | D3: GP_Margin | E3: Discount_Value | F3: Discount_Rate | G3: Promo_Spend | H3: Contribution_Profit | I3: Contribution_Margin | J3: Units | K3: ASP
A4: 2025-01 | B4: 29504.47 | C4: 11666.09 | D4: 0.3954 | E4: 4037.12 | F4: 0.1204 | G4: 61.32 | H4: 10754.07 | I4: 0.3645 | J4: 3418 | K4: 8.63
A5: 2025-02 | B5: 22669.04 | C5: 8788.03 | D5: 0.3877 | E5: 3294.31 | F5: 0.1269 | G5: 85.62 | H5: 8101.37 | I5: 0.3574 | J5: 2887 | K5: 7.85
A6: 2025-03 | B6: 42015.55 | C6: 16786.02 | D6: 0.3995 | E6: 6354.03 | F6: 0.1314 | G6: 122.83 | H6: 15592.97 | I6: 0.3711 | J6: 5070 | K6: 8.29
A7: 2025-04 | B7: 24286.62 | C7: 9929.36 | D7: 0.4088 | E7: 3889.74 | F7: 0.138 | G7: 122.27 | H7: 9209.56 | I7: 0.3792 | J7: 3428 | K7: 7.08
A8: 2025-05 | B8: 23245.07 | C8: 9276.12 | D8: 0.3991 | E8: 3639.76 | F8: 0.1354 | G8: 76.43 | H8: 8621.69 | I8: 0.3709 | J8: 2903 | K8: 8.01
A9: 2025-06 | B9: 27675.55 | C9: 10927.16 | D9: 0.3948 | E9: 3930.4 | F9: 0.1244 | G9: 99.09 | H9: 10122.15 | I9: 0.3657 | J9: 3373 | K9: 8.21
A10: 2025-07 | B10: 28634.19 | C10: 11604.6 | D10: 0.4053 | E10: 4669.16 | F10: 0.1402 | G10: 91.31 | H10: 10813.99 | I10: 0.3777 | J10: 3753 | K10: 7.63
A11: 2025-08 | B11: 26049.87 | C11: 10099.82 | D11: 0.3877 | E11: 4206.83 | F11: 0.139 | G11: 77.19 | H11: 9374.38 | I11: 0.3599 | J11: 3219 | K11: 8.09
A12: 2025-09 | B12: 30432 | C12: 12130.79 | D12: 0.3986 | E12: 4575.6 | F12: 0.1307 | G12: 102.24 | H12: 11226.15 | I12: 0.3689 | J12: 3943 | K12: 7.72
A13: 2025-10 | B13: 34970.59 | C13: 14150.65 | D13: 0.4046 | E13: 5658.13 | F13: 0.1393 | G13: 165.67 | H13: 13136.11 | I13: 0.3756 | J13: 4482 | K13: 7.8
A14: 2025-11 | B14: 46752.4 | C14: 18024.49 | D14: 0.3855 | E14: 7433.61 | F14: 0.1372 | G14: 122.56 | H14: 16737.11 | I14: 0.358 | J14: 5804 | K14: 8.06
A15: 2025-12 | B15: 24489.08 | C15: 9861 | D15: 0.4027 | E15: 4133.3 | F15: 0.1444 | G15: 75.58 | H15: 9197.89 | I15: 0.3756 | J15: 3172 | K15: 7.72
... A24: 2026-09 | B24: 31916.85 | C24: 12265.47 | D24: 0.3843 | E24: 4955.64 | F24: 0.1344 | G24: 82.42 | H24: 11351.21 | I24: 0.3556 | J24: 3704 | K24: 8.62

Sheet Dashboard
A1: Commercial Finance Dashboard — Pricing, Margin & Profitability
A3: SQL-powered commercial analysis | Jan-2025 to Sep-2026 | Synthetic FMCG portfolio
A5: Net Revenue | D5: Gross Profit | G5: Gross Margin | J5: Contribution Profit
A6: ="£"&TEXT(SUM('Channel Analysis'!B4:B9),"#,##0") -> £632,781 | D6: ="£"&TEXT(SUM('Channel Analysis'!C4:C9),"#,##0") -> £249,537 | G6: =TEXT(SUM('Channel Analysis'!C4:C9)/SUM('Channel Analysis'!B4:B9),"0.0%") -> 39.4% | J6: ="£"&TEXT(SUM('Channel Analysis'!I4:I9),"#,##0") -> £231,064
A9: Contribution Margin | D9: Discount Value | G9: Discount Rate | J9: Promo Spend
A10: =TEXT(SUM('Channel Analysis'!I4:I9)/SUM('Channel Analysis'!B4:B9),"0.0%") -> 36.5% | D10: ="£"&TEXT(SUM('Channel Analysis'!E4:E9),"#,##0") -> £98,048 | G10: =TEXT(SUM('Channel Analysis'!E4:E9)/(SUM('Channel Analysis'!B4:B9)+SUM('Channel Analysis'!E4:E9)),"0.0%") -> 13.4% | J10: ="£"&TEXT(SUM('Channel Analysis'!H4:H9),"#,##0") -> £2,215
A14: Monthly Commercial Trend
A15: Month | B15: Net Revenue | C15: Contribution Margin
A16: 2025-01 | B16: 29504.47 | C16: 0.3645
A17: 2025-02 | B17: 22669.04 | C17: 0.3574
A18: 2025-03 | B18: 42015.55 | C18: 0.3711
A19: 2025-04 | B19: 24286.62 | C19: 0.3792
A20: 2025-05 | B20: 23245.07 | C20: 0.3709
A21: 2025-06 | B21: 27675.55 | C21: 0.3657
A22: 2025-07 | B22: 28634.19 | C22: 0.3777
A23: 2025-08 | B23: 26049.87 | C23: 0.3599
A24: 2025-09 | B24: 30432 | C24: 0.3689 | H24: Channel Contribution Performance
A25: 2025-10 | B25: 34970.59 | C25: 0.3756 | H25: Channel | I25: Contribution Profit | J25: Contribution Margin
A26: 2025-11 | B26: 46752.4 | C26: 0.358 | H26: DTC | I26: 50160.32 | J26: 0.3908
A27: 2025-12 | B27: 24489.08 | C27: 0.3756 | H27: Baby Specialist | I27: 40427.52 | J27: 0.377
A28: 2026-01 | B28: 22723.12 | C28: 0.3573 | H28: Pharmacy | I28: 40367.2 | J28: 0.3811
A29: 2026-02 | B29: 20706.29 | C29: 0.3642 | H29: Online Marketplace | I29: 35411.8 | J29: 0.3372
A30: 2026-03 | B30: 46197.59 | C30: 0.3645 | H30: Wholesale | I30: 32818.23 | J30: 0.3372
A31: 2026-04 | B31: 33429.4 | C31: 0.3784 | H31: Grocery | I31: 31878.73 | J31: 0.3586
A32: 2026-05 | B32: 30923.21 | C32: 0.3677
A33: 2026-06 | B33: 26369 | C33: 0.3438
A34: 2026-07 | B34: 28712.72 | C34: 0.3555 | H34: Category Profitability
A35: 2026-08 | B35: 31078.9 | C35: 0.3549 | H35: Category | I35: Net Revenue | J35: Contribution Profit | K35: Contribution Margin
A36: 2026-09 | B36: 31916.85 | C36: 0.3556 | H36: Diapers | I36: 298369.65 | J36: 102159.29 | K36: 0.3424
H37: Wipes | I37: 143676.81 | J37: 51973.18 | K37: 0.3617
H38: Baby Bath | I38: 62975.51 | J38: 26609.47 | K38: 0.4225
H39: Skincare | I39: 57161.69 | J39: 24612.23 | K39: 0.4306
H40: Feeding | I40: 42507.21 | J40: 16294.99 | K40: 0.3833
H41: Nursery | I41: 28090.59 | J41: 9414.64 | K41: 0.3352
A61: Management interpretation prompts
A62: 1 | B62: Which channels create the most contribution profit—not just revenue?
A63: 2 | B63: Where is discounting eroding commercial value?
A64: 3 | B64: Which categories have strong revenue but weak contribution margin?
A65: 4 | B65: Which customers require repricing, lower discounts or cost-to-serve action?
A66: 5 | B66: Which commercial actions should be prioritised before the next pricing round?

Sheet Data Dictionary
A1: Data Dictionary & Commercial Definitions
A3: Field / Metric | B3: Definition | C3: Unit | D3: Layer | E3: Primary Table | F3: Commercial Relevance | G3: Source
A4: Gross Sales | B4: Units × list price before discount | C4: £ | D4: Fact | E4: Fact Sales | F4: Starting sales value | G4: Synthetic ERP extract
A5: Discount % | B5: Discount as % gross sales | C5: % | D5: Fact | E5: Fact Sales | F5: Pricing governance | G5: Synthetic ERP extract
A6: Net Revenue | B6: Gross sales less discount | C6: £ | D6: Fact | E6: Fact Sales | F6: Realised revenue | G6: Calculated in data pipeline
A7: COGS | B7: Units × unit COGS | C7: £ | D7: Fact | E7: Fact Sales | F7: Product economics | G7: Calculated in data pipeline
A8: Gross Profit | B8: Net revenue − COGS | C8: £ | D8: Fact | E8: Fact Sales | F8: Product margin | G8: Calculated in data pipeline
A9: Gross Margin | B9: Gross profit / net revenue | C9: % | D9: Analysis | E9: SQL outputs | F9: Profitability KPI | G9: SQL
A10: Freight | B10: Channel freight rate × net revenue | C10: £ | D10: Fact | E10: Fact Sales | F10: Cost-to-serve | G10: Calculated in data pipeline
A11: Promo Spend | B11: Promotional support cost | C11: £ | D11: Fact | E11: Fact Sales | F11: Trade investment | G11: Synthetic input
A12: Contribution Profit | B12: GP − freight − promo spend | C12: £ | D12: Analysis | E12: SQL outputs | F12: Commercial value | G12: SQL
A13: Contribution Margin | B13: Contribution profit / net revenue | C13: % | D13: Analysis | E13: SQL outputs | F13: Commercial Finance KPI | G13: SQL
A14: Customer Tier | B14: Strategic / Core / Long Tail | C14: text | D14: Dimension | E14: Dim Customer | F14: Segmentation | G14: Synthetic master data
A15: Channel | B15: Route to market | C15: text | D15: Dimension | E15: Dim Customer | F15: Route-to-market economics | G15: Synthetic master data
A18: V2 Metrics
A19: Target Discount | B19: Synthetic pricing-policy benchmark by channel, tier and promo mix | C19: % | D19: Formula / assumption | E19: Discount Leakage | F19: Pricing governance | G19: Portfolio assumption
A20: Discount Leakage | B20: Gross sales × max(actual discount − target discount, 0) | C20: £ | D20: Formula | E20: Discount Leakage | F20: Potential pricing leakage | G20: Modelled, not realised
A21: Potential Recapture | B21: Discount leakage × realisation factor | C21: £ | D21: Formula | E21: Discount Leakage | F21: Repricing opportunity | G21: 70% synthetic realisation assumption
A22: Customer Quadrant | B22: Revenue / contribution-margin matrix classification | C22: text | D22: Formula | E22: Customer Matrix | F22: Customer strategy | G22: Median thresholds
A23: Promo ROI Proxy | B23: Incremental contribution proxy / promo spend | C23: x | D23: Derived | E23: Promo Effectiveness | F23: Promotion efficiency | G23: Observational; not causal
A24: Revenue HHI | B24: Sum of squared customer revenue shares | C24: index | D24: Derived | E24: Customer Concentration | F24: Concentration diagnostic | G24: Synthetic portfolio
A25: SKU Portfolio Action | B25: Revenue / margin quadrant classification | C25: text | D25: Formula | E25: SKU Rationalisation | F25: Portfolio prioritisation | G25: Median thresholds
A26: Price Effect | B26: Current units × change in ASP | C26: £ | D26: Formula | E26: PVM Analysis V2 | F26: Price realisation | G26: YTD 2026 vs YTD 2025
A27: Volume Effect | B27: Change in total units × prior mix × prior ASP | C27: £ | D27: Formula | E27: PVM Analysis V2 | F27: Volume growth | G27: YTD 2026 vs YTD 2025
A28: Mix Effect | B28: Current total units × change in category mix × prior ASP | C28: £ | D28: Formula | E28: PVM Analysis V2 | F28: Portfolio mix | G28: YTD 2026 vs YTD 2025
A31: V3 Metrics
A32: Excess Discount Recovery | B32: Share of customer discount above policy assumed to be recovered | C32: % | D32: Scenario input | E32: Pricing Scenarios | F32: Repricing scenario | G32: Conservative / Base / Stretch
A33: Volume Retention | B33: Share of volume assumed to remain after repricing | C33: % | D33: Scenario input | E33: Pricing Scenarios | F33: Repricing risk | G33: Synthetic scenario assumption
A34: Price Recapture on Retained Business | B34: Leakage × recovery % × retention % | C34: £ | D34: Formula | E34: Pricing Scenarios | F34: Price upside | G34: Modelled
A35: Contribution Lost from Attrition | B35: Existing contribution × (1 − retention %) | C35: £ | D35: Formula | E35: Pricing Scenarios | F35: Downside risk | G35: Modelled
A36: Net Contribution Uplift | B36: Price recapture less contribution lost from attrition | C36: £ | D36: Formula | E36: Pricing Scenarios | F36: Risk-adjusted repricing value | G36: Modelled
A37: Customer Action Register | B37: Prioritised customer actions with owner, status and timing | C37: workflow | D37: Input / linked | E37: Customer Action Register | F37: Commercial cadence | G37: Portfolio workflow

Sheet Power BI Measures
A1: Power BI Measure Library — V1
A3: Prepared DAX measures for the later Power BI build. V1 is Power BI-ready; a PBIX dashboard is not yet claimed.
A5: Measure | B5: DAX | C5: Purpose
A6: Net Revenue | B6: Net Revenue = SUM(FactSales[Net_Revenue]) | C6: Commercial revenue
A7: Gross Profit | B7: Gross Profit = SUM(FactSales[Gross_Profit]) | C7: Product margin
A8: Gross Margin % | B8: Gross Margin % = DIVIDE([Gross Profit],[Net Revenue]) | C8: Margin rate
A9: Discount Value | B9: Discount Value = SUM(FactSales[Discount_Value]) | C9: Discount leakage
A10: Discount Rate % | B10: Discount Rate % = DIVIDE([Discount Value],[Net Revenue]+[Discount Value]) | C10: Discount intensity
A11: Promo Spend | B11: Promo Spend = SUM(FactSales[Promo_Spend]) | C11: Trade investment
A12: Contribution Profit | B12: Contribution Profit = SUM(FactSales[Contribution_Profit]) | C12: Profit after cost-to-serve
A13: Contribution Margin % | B13: Contribution Margin % = DIVIDE([Contribution Profit],[Net Revenue]) | C13: Commercial profitability
A14: Units | B14: Units = SUM(FactSales[Units]) | C14: Volume
A15: ASP | B15: ASP = DIVIDE([Net Revenue],[Units]) | C15: Realised selling price

Sheet Discount Leakage
A1: Discount Leakage & Repricing Opportunities
A3: Pricing-policy benchmark is synthetic. Potential recapture applies a 70% realisation factor and is not a realised saving.
A5: Customer ID | B5: Customer Name | C5: Channel | D5: Tier | E5: Gross Sales (£) | F5: Actual Discount % | G5: Base Target % | H5: Tier Premium % | I5: Promo Gross Share % | J5: Promo Adjustment % | K5: Target Discount % | L5: Excess Discount % | M5: Gross Leakage (£) | N5: Recapture Factor | O5: Potential Recapture (£) | P5: Contribution Margin | Q5: Commercial Action
A6: C001 | B6: Northgate Grocers 01 | C6: Grocery | D6: Strategic | E6: 27910.74 | F6: 0.16467481 | G6: =IFERROR(VLOOKUP(C6,Assumptions!$A$23:$B$28,2,FALSE),0) -> 0.12 | H6: =IF(D6="Strategic",Assumptions!$B$31,IF(D6="Core",Assumptions!$B$32,Assumptions!$B$33)) -> 0.02 | I6: 0.25106715 | J6: =I6*Assumptions!$B$34 -> 0.005021343 | K6: =G6+H6+J6 -> 0.14502134 | L6: =MAX(F6-K6,0) -> 0.019653466 | M6: =E6*L6 -> 548.54277 | N6: =Assumptions!$B$35 -> 0.7 | O6: =M6*N6 -> 383.97994 | P6: 0.3531389 | Q6: =IF(O6>=100,"Priority repricing",IF(L6>=1%,"Review discount","Within policy")) -> Priority repricing
A7: C061 | B7: FamilyCare Wholesale 01 | C7: Wholesale | D7: Strategic | E7: 21132.51 | F7: 0.2090308 | G7: =IFERROR(VLOOKUP(C7,Assumptions!$A$23:$B$28,2,FALSE),0) -> 0.16 | H7: =IF(D7="Strategic",Assumptions!$B$31,IF(D7="Core",Assumptions!$B$32,Assumptions!$B$33)) -> 0.02 | I7: 0.30271747 | J7: =I7*Assumptions!$B$34 -> 0.0060543494 | K7: =G7+H7+J7 -> 0.18605435 | L7: =MAX(F7-K7,0) -> 0.022976448 | M7: =E7*L7 -> 485.55001 | N7: =Assumptions!$B$35 -> 0.7 | O7: =M7*N7 -> 339.88501 | P7: 0.33949155 | Q7: =IF(O7>=100,"Priority repricing",IF(L7>=1%,"Review discount","Within policy")) -> Priority repricing
A8: C063 | B8: FamilyCare Wholesale 03 | C8: Wholesale | D8: Strategic | E8: 22454.98 | F8: 0.1993856 | G8: =IFERROR(VLOOKUP(C8,Assumptions!$A$23:$B$28,2,FALSE),0) -> 0.16 | H8: =IF(D8="Strategic",Assumptions!$B$31,IF(D8="Core",Assumptions!$B$32,Assumptions!$B$33)) -> 0.02 | I8: 0.070433374 | J8: =I8*Assumptions!$B$34 -> 0.0014086675 | K8: =G8+H8+J8 -> 0.18140867 | L8: =MAX(F8-K8,0) -> 0.017976934 | M8: =E8*L8 -> 403.67168 | N8: =Assumptions!$B$35 -> 0.7 | O8: =M8*N8 -> 282.57018 | P8: 0.33092259 | Q8: =IF(O8>=100,"Priority repricing",IF(L8>=1%,"Review discount","Within policy")) -> Priority repricing
A9: C033 | B9: HomeCart Online 03 | C9: Online Marketplace | D9: Strategic | E9: 25671.1 | F9: 0.179612 | G9: =IFERROR(VLOOKUP(C9,Assumptions!$A$23:$B$28,2,FALSE),0) -> 0.14 | H9: =IF(D9="Strategic",Assumptions!$B$31,IF(D9="Core",Assumptions!$B$32,Assumptions!$B$33)) -> 0.02 | I9: 0.26805006 | J9: =I9*Assumptions!$B$34 -> 0.0053610013 | K9: =G9+H9+J9 -> 0.165361 | L9: =MAX(F9-K9,0) -> 0.014250999 | M9: =E9*L9 -> 365.83883 | N9: =Assumptions!$B$35 -> 0.7 | O9: =M9*N9 -> 256.08718 | P9: 0.31575939 | Q9: =IF(O9>=100,"Priority repricing",IF(L9>=1%,"Review discount","Within policy")) -> Priority repricing
A10: C047 | B10: Direct Family Customer 02 | C10: DTC | D10: Strategic | E10: 30978.95 | F10: 0.081698949 | G10: =IFERROR(VLOOKUP(C10,Assumptions!$A$23:$B$28,2,FALSE),0) -> 0.05 | H10: =IF(D10="Strategic",Assumptions!$B$31,IF(D10="Core",Assumptions!$B$32,Assumptions!$B$33)) -> 0.02 | I10: 0.094512564 | J10: =I10*Assumptions!$B$34 -> 0.0018902513 | K10: =G10+H10+J10 -> 0.071890251 | L10: =MAX(F10-K10,0) -> 0.0098086982 | M10: =E10*L10 -> 303.86317 | N10: =Assumptions!$B$35 -> 0.7 | O10: =M10*N10 -> 212.70422 | P10: 0.37798374 | Q10: =IF(O10>=100,"Priority repricing",IF(L10>=1%,"Review discount","Within policy")) -> Priority repricing
A11: C018 | B11: WellSpring Pharmacy 03 | C11: Pharmacy | D11: Strategic | E11: 23191.93 | F11: 0.13566147 | G11: =IFERROR(VLOOKUP(C11,Assumptions!$A$23:$B$28,2,FALSE),0) -> 0.1 | H11: =IF(D11="Strategic",Assumptions!$B$31,IF(D11="Core",Assumptions!$B$32,Assumptions!$B$33)) -> 0.02 | I11: 0.24910863 | J11: =I11*Assumptions!$B$34 -> 0.0049821727 | K11: =G11+H11+J11 -> 0.12498217 | L11: =MAX(F11-K11,0) -> 0.010679294 | M11: =E11*L11 -> 247.67345 | N11: =Assumptions!$B$35 -> 0.7 | O11: =M11*N11 -> 173.37141 | P11: 0.38243352 | Q11: =IF(O11>=100,"Priority repricing",IF(L11>=1%,"Review discount","Within policy")) -> Priority repricing
A12: C077 | B12: LittleNest Retail 02 | C12: Baby Specialist | D12: Strategic | E12: 27183.76 | F12: 0.12358106 | G12: =IFERROR(VLOOKUP(C12,Assumptions!$A$23:$B$28,2,FALSE),0) -> 0.09 | H12: =IF(D12="Strategic",Assumptions!$B$31,IF(D12="Core",Assumptions!$B$32,Assumptions!$B$33)) -> 0.02 | I12: 0.24823093 | J12: =I12*Assumptions!$B$34 -> 0.0049646186 | K12: =G12+H12+J12 -> 0.11496462 | L12: =MAX(F12-K12,0) -> 0.0086164408 | M12: =E12*L12 -> 234.22726 | N12: =Assumptions!$B$35 -> 0.7 | O12: =M12*N12 -> 163.95908 | P12: 0.36921248 | Q12: =IF(O12>=100,"Priority repricing",IF(L12>=1%,"Review discount","Within policy")) -> Priority repricing
A13: C032 | B13: HomeCart Online 02 | C13: Online Marketplace | D13: Strategic | E13: 24910.76 | F13: 0.17193183 | G13: =IFERROR(VLOOKUP(C13,Assumptions!$A$23:$B$28,2,FALSE),0) -> 0.14 | H13: =IF(D13="Strategic",Assumptions!$B$31,IF(D13="Core",Assumptions!$B$32,Assumptions!$B$33)) -> 0.02 | I13: 0.18215582 | J13: =I13*Assumptions!$B$34 -> 0.0036431165 | K13: =G13+H13+J13 -> 0.16364312 | L13: =MAX(F13-K13,0) -> 0.0082887136 | M13: =E13*L13 -> 206.47815 | N13: =Assumptions!$B$35 -> 0.7 | O13: =M13*N13 -> 144.53471 | P13: 0.33133209 | Q13: =IF(O13>=100,"Priority repricing",IF(L13>=1%,"Review discount","Within policy")) -> Priority repricing
A14: C062 | B14: FamilyCare Wholesale 02 | C14: Wholesale | D14: Strategic | E14: 19253.07 | F14: 0.19087436 | G14: =IFERROR(VLOOKUP(C14,Assumptions!$A$23:$B$28,2,FALSE),0) -> 0.16 | H14: =IF(D14="Strategic",Assumptions!$B$31,IF(D14="Core",Assumptions!$B$32,Assumptions!$B$33)) -> 0.02 | I14: 0.070660939 | J14: =I14*Assumptions!$B$34 -> 0.0014132188 | K14: =G14+H14+J14 -> 0.18141322 | L14: =MAX(F14-K14,0) -> 0.0094611437 | M14: =E14*L14 -> 182.15606 | N14: =Assumptions!$B$35 -> 0.7 | O14: =M14*N14 -> 127.50924 | P14: 0.30827919 | Q14: =IF(O14>=100,"Priority repricing",IF(L14>=1%,"Review discount","Within policy")) -> Priority repricing
A15: C048 | B15: Direct Family Customer 03 | C15: DTC | D15: Strategic | E15: 22586 | F15: 0.083759327 | G15: =IFERROR(VLOOKUP(C15,Assumptions!$A$23:$B$28,2,FALSE),0) -> 0.05 | H15: =IF(D15="Strategic",Assumptions!$B$31,IF(D15="Core",Assumptions!$B$32,Assumptions!$B$33)) -> 0.02 | I15: 0.32381165 | J15: =I15*Assumptions!$B$34 -> 0.0064762331 | K15: =G15+H15+J15 -> 0.076476233 | L15: =MAX(F15-K15,0) -> 0.0072830935 | M15: =E15*L15 -> 164.49595 | N15: =Assumptions!$B$35 -> 0.7 | O15: =M15*N15 -> 115.14717 | P15: 0.39021647 | Q15: =IF(O15>=100,"Priority repricing",IF(L15>=1%,"Review discount","Within policy")) -> Priority repricing
A16: C016 | B16: WellSpring Pharmacy 01 | C16: Pharmacy | D16: Strategic | E16: 19627.16 | F16: 0.13075218 | G16: =IFERROR(VLOOKUP(C16,Assumptions!$A$23:$B$28,2,FALSE),0) -> 0.1 | H16: =IF(D16="Strategic",Assumptions!$B$31,IF(D16="Core",Assumptions!$B$32,Assumptions!$B$33)) -> 0.02 | I16: 0.1426727 | J16: =I16*Assumptions!$B$34 -> 0.0028534541 | K16: =G16+H16+J16 -> 0.12285345 | L16: =MAX(F16-K16,0) -> 0.0078987282 | M16: =E16*L16 -> 155.0296 | N16: =Assumptions!$B$35 -> 0.7 | O16: =M16*N16 -> 108.52072 | P16: 0.3940508 | Q16: =IF(O16>=100,"Priority repricing",IF(L16>=1%,"Review discount","Within policy")) -> Priority repricing
A17: C008 | B17: Northgate Grocers 08 | C17: Grocery | D17: Core | E17: 8306.34 | F17: 0.15201467 | G17: =IFERROR(VLOOKUP(C17,Assumptions!$A$23:$B$28,2,FALSE),0) -> 0.12 | H17: =IF(D17="Strategic",Assumptions!$B$31,IF(D17="Core",Assumptions!$B$32,Assumptions!$B$33)) -> 0.01 | I17: 0.30981636 | J17: =I17*Assumptions!$B$34 -> 0.0061963271 | K17: =G17+H17+J17 -> 0.13619633 | L17: =MAX(F17-K17,0) -> 0.015818346 | M17: =E17*L17 -> 131.39256 | N17: =Assumptions!$B$35 -> 0.7 | O17: =M17*N17 -> 91.974791 | P17: 0.36201643 | Q17: =IF(O17>=100,"Priority repricing",IF(L17>=1%,"Review discount","Within policy")) -> Review discount
... A95: C089 | B95: LittleNest Retail 14 | C95: Baby Specialist | D95: Long Tail | E95: 1266.57 | F95: 0.089839874 | G95: =IFERROR(VLOOKUP(C95,Assumptions!$A$23:$B$28,2,FALSE),0) -> 0.09 | H95: =IF(D95="Strategic",Assumptions!$B$31,IF(D95="Core",Assumptions!$B$32,Assumptions!$B$33)) -> 0 | I95: 0 | J95: =I95*Assumptions!$B$34 -> 0 | K95: =G95+H95+J95 -> 0.09 | L95: =MAX(F95-K95,0) -> 0 | M95: =E95*L95 -> 0 | N95: =Assumptions!$B$35 -> 0.7 | O95: =M95*N95 -> 0 | P95: 0.37547231 | Q95: =IF(O95>=100,"Priority repricing",IF(L95>=1%,"Review discount","Within policy")) -> Within policy
A99: Leakage summary | H99: Customer | I99: Potential Recapture (£)
A100: Metric | B100: Value | C100: Interpretation | D100: Source | H100: Northgate Grocers 01 | I100: =O6 -> 383.97994
A101: Gross Discount Leakage | B101: =SUM(M6:M95) -> 5536.2442 | C101: Amount above synthetic pricing policy | D101: Calculated | H101: FamilyCare Wholesale 01 | I101: =O7 -> 339.88501
A102: Potential Recapture | B102: =SUM(O6:O95) -> 3875.371 | C102: 70% modelled realisation of leakage | D102: Calculated | H102: FamilyCare Wholesale 03 | I102: =O8 -> 282.57018
A103: Priority Repricing Accounts | B103: =COUNTIF(Q6:Q95,"Priority repricing") -> 11 | C103: Accounts with ≥ £100 potential recapture | D103: Calculated | H103: HomeCart Online 03 | I103: =O9 -> 256.08718
A104: Accounts Above Policy | B104: =COUNTIF(L6:L95,">0") -> 57 | C104: Accounts with excess discount > 0 | D104: Calculated | H104: Direct Family Customer 02 | I104: =O10 -> 212.70422
H105: WellSpring Pharmacy 03 | I105: =O11 -> 173.37141
H106: LittleNest Retail 02 | I106: =O12 -> 163.95908
H107: HomeCart Online 02 | I107: =O13 -> 144.53471
H108: FamilyCare Wholesale 02 | I108: =O14 -> 127.50924
H109: Direct Family Customer 03 | I109: =O15 -> 115.14717

Sheet Customer Matrix
A1: Customer Profitability Matrix
A3: Segmentation uses median revenue and median contribution margin from the synthetic customer portfolio.
A5: Quadrant thresholds
A6: Metric | B6: Threshold
A7: Median Customer Revenue | B7: =MEDIAN(E12:E101) -> 5571.1864
A8: Median Contribution Margin | B8: =MEDIAN(G12:G101) -> 0.37451585
A11: Customer ID | B11: Customer Name | C11: Channel | D11: Tier | E11: Net Revenue (£) | F11: Contribution Profit (£) | G11: Contribution Margin | H11: Discount Rate | I11: Revenue vs Median | J11: Margin vs Median | K11: Quadrant | L11: Recommended Focus
A12: C046 | B12: Direct Family Customer 01 | C12: DTC | D12: Strategic | E12: 29695.553 | F12: 11810.533 | G12: 0.39772061 | H12: 0.074005425 | I12: =IF(E12>=$B$7,"High","Low") -> High | J12: =IF(G12>=$B$8,"High","Low") -> High | K12: =IF(AND(I12="High",J12="High"),"Protect / Grow",IF(AND(I12="High",J12="Low"),"Reprice / Cost-to-Serve",IF(AND(I12="Low",J12="High"),"Develop / Grow","Review / Deprioritise"))) -> Protect / Grow | L12: =IF(K12="Protect / Grow","Defend relationship and expand profitable volume",IF(K12="Reprice / Cost-to-Serve","Review discounts, freight and service economics",IF(K12="Develop / Grow","Target selective volume growth","Review account economics and strategic fit"))) -> Defend relationship and expand profitable volume
A13: C047 | B13: Direct Family Customer 02 | C13: DTC | D13: Strategic | E13: 28448.002 | F13: 10752.882 | G13: 0.37798374 | H13: 0.081698949 | I13: =IF(E13>=$B$7,"High","Low") -> High | J13: =IF(G13>=$B$8,"High","Low") -> High | K13: =IF(AND(I13="High",J13="High"),"Protect / Grow",IF(AND(I13="High",J13="Low"),"Reprice / Cost-to-Serve",IF(AND(I13="Low",J13="High"),"Develop / Grow","Review / Deprioritise"))) -> Protect / Grow | L13: =IF(K13="Protect / Grow","Defend relationship and expand profitable volume",IF(K13="Reprice / Cost-to-Serve","Review discounts, freight and service economics",IF(K13="Develop / Grow","Target selective volume growth","Review account economics and strategic fit"))) -> Defend relationship and expand profitable volume
A14: C077 | B14: LittleNest Retail 02 | C14: Baby Specialist | D14: Strategic | E14: 23824.362 | F14: 8796.2518 | G14: 0.36921248 | H14: 0.12358106 | I14: =IF(E14>=$B$7,"High","Low") -> High | J14: =IF(G14>=$B$8,"High","Low") -> Low | K14: =IF(AND(I14="High",J14="High"),"Protect / Grow",IF(AND(I14="High",J14="Low"),"Reprice / Cost-to-Serve",IF(AND(I14="Low",J14="High"),"Develop / Grow","Review / Deprioritise"))) -> Reprice / Cost-to-Serve | L14: =IF(K14="Protect / Grow","Defend relationship and expand profitable volume",IF(K14="Reprice / Cost-to-Serve","Review discounts, freight and service economics",IF(K14="Develop / Grow","Target selective volume growth","Review account economics and strategic fit"))) -> Review discounts, freight and service economics
A15: C001 | B15: Northgate Grocers 01 | C15: Grocery | D15: Strategic | E15: 23314.544 | F15: 8233.2724 | G15: 0.3531389 | H15: 0.16467481 | I15: =IF(E15>=$B$7,"High","Low") -> High | J15: =IF(G15>=$B$8,"High","Low") -> Low | K15: =IF(AND(I15="High",J15="High"),"Protect / Grow",IF(AND(I15="High",J15="Low"),"Reprice / Cost-to-Serve",IF(AND(I15="Low",J15="High"),"Develop / Grow","Review / Deprioritise"))) -> Reprice / Cost-to-Serve | L15: =IF(K15="Protect / Grow","Defend relationship and expand profitable volume",IF(K15="Reprice / Cost-to-Serve","Review discounts, freight and service economics",IF(K15="Develop / Grow","Target selective volume growth","Review account economics and strategic fit"))) -> Review discounts, freight and service economics
A16: C031 | B16: HomeCart Online 01 | C16: Online Marketplace | D16: Strategic | E16: 21393.976 | F16: 7298.4322 | G16: 0.34114427 | H16: 0.17332026 | I16: =IF(E16>=$B$7,"High","Low") -> High | J16: =IF(G16>=$B$8,"High","Low") -> Low | K16: =IF(AND(I16="High",J16="High"),"Protect / Grow",IF(AND(I16="High",J16="Low"),"Reprice / Cost-to-Serve",IF(AND(I16="Low",J16="High"),"Develop / Grow","Review / Deprioritise"))) -> Reprice / Cost-to-Serve | L16: =IF(K16="Protect / Grow","Defend relationship and expand profitable volume",IF(K16="Reprice / Cost-to-Serve","Review discounts, freight and service economics",IF(K16="Develop / Grow","Target selective volume growth","Review account economics and strategic fit"))) -> Review discounts, freight and service economics
A17: C033 | B17: HomeCart Online 03 | C17: Online Marketplace | D17: Strategic | E17: 21060.262 | F17: 6649.9756 | G17: 0.31575939 | H17: 0.179612 | I17: =IF(E17>=$B$7,"High","Low") -> High | J17: =IF(G17>=$B$8,"High","Low") -> Low | K17: =IF(AND(I17="High",J17="High"),"Protect / Grow",IF(AND(I17="High",J17="Low"),"Reprice / Cost-to-Serve",IF(AND(I17="Low",J17="High"),"Develop / Grow","Review / Deprioritise"))) -> Reprice / Cost-to-Serve | L17: =IF(K17="Protect / Grow","Defend relationship and expand profitable volume",IF(K17="Reprice / Cost-to-Serve","Review discounts, freight and service economics",IF(K17="Develop / Grow","Target selective volume growth","Review account economics and strategic fit"))) -> Review discounts, freight and service economics
A18: C048 | B18: Direct Family Customer 03 | C18: DTC | D18: Strategic | E18: 20694.212 | F18: 8075.2223 | G18: 0.39021647 | H18: 0.083759327 | I18: =IF(E18>=$B$7,"High","Low") -> High | J18: =IF(G18>=$B$8,"High","Low") -> High | K18: =IF(AND(I18="High",J18="High"),"Protect / Grow",IF(AND(I18="High",J18="Low"),"Reprice / Cost-to-Serve",IF(AND(I18="Low",J18="High"),"Develop / Grow","Review / Deprioritise"))) -> Protect / Grow | L18: =IF(K18="Protect / Grow","Defend relationship and expand profitable volume",IF(K18="Reprice / Cost-to-Serve","Review discounts, freight and service economics",IF(K18="Develop / Grow","Target selective volume growth","Review account economics and strategic fit"))) -> Defend relationship and expand profitable volume
A19: C032 | B19: HomeCart Online 02 | C19: Online Marketplace | D19: Strategic | E19: 20627.807 | F19: 6834.6545 | G19: 0.33133209 | H19: 0.17193183 | I19: =IF(E19>=$B$7,"High","Low") -> High | J19: =IF(G19>=$B$8,"High","Low") -> Low | K19: =IF(AND(I19="High",J19="High"),"Protect / Grow",IF(AND(I19="High",J19="Low"),"Reprice / Cost-to-Serve",IF(AND(I19="Low",J19="High"),"Develop / Grow","Review / Deprioritise"))) -> Reprice / Cost-to-Serve | L19: =IF(K19="Protect / Grow","Defend relationship and expand profitable volume",IF(K19="Reprice / Cost-to-Serve","Review discounts, freight and service economics",IF(K19="Develop / Grow","Target selective volume growth","Review account economics and strategic fit"))) -> Review discounts, freight and service economics
A20: C018 | B20: WellSpring Pharmacy 03 | C20: Pharmacy | D20: Strategic | E20: 20045.679 | F20: 7666.1395 | G20: 0.38243352 | H20: 0.13566147 | I20: =IF(E20>=$B$7,"High","Low") -> High | J20: =IF(G20>=$B$8,"High","Low") -> High | K20: =IF(AND(I20="High",J20="High"),"Protect / Grow",IF(AND(I20="High",J20="Low"),"Reprice / Cost-to-Serve",IF(AND(I20="Low",J20="High"),"Develop / Grow","Review / Deprioritise"))) -> Protect / Grow | L20: =IF(K20="Protect / Grow","Defend relationship and expand profitable volume",IF(K20="Reprice / Cost-to-Serve","Review discounts, freight and service economics",IF(K20="Develop / Grow","Target selective volume growth","Review account economics and strategic fit"))) -> Defend relationship and expand profitable volume
A21: C078 | B21: LittleNest Retail 03 | C21: Baby Specialist | D21: Strategic | E21: 19839.5 | F21: 7453.0119 | G21: 0.3756653 | H21: 0.11530764 | I21: =IF(E21>=$B$7,"High","Low") -> High | J21: =IF(G21>=$B$8,"High","Low") -> High | K21: =IF(AND(I21="High",J21="High"),"Protect / Grow",IF(AND(I21="High",J21="Low"),"Reprice / Cost-to-Serve",IF(AND(I21="Low",J21="High"),"Develop / Grow","Review / Deprioritise"))) -> Protect / Grow | L21: =IF(K21="Protect / Grow","Defend relationship and expand profitable volume",IF(K21="Reprice / Cost-to-Serve","Review discounts, freight and service economics",IF(K21="Develop / Grow","Target selective volume growth","Review account economics and strategic fit"))) -> Defend relationship and expand profitable volume
A22: C017 | B22: WellSpring Pharmacy 02 | C22: Pharmacy | D22: Strategic | E22: 19566.794 | F22: 7153.0515 | G22: 0.36557095 | H22: 0.12629869 | I22: =IF(E22>=$B$7,"High","Low") -> High | J22: =IF(G22>=$B$8,"High","Low") -> Low | K22: =IF(AND(I22="High",J22="High"),"Protect / Grow",IF(AND(I22="High",J22="Low"),"Reprice / Cost-to-Serve",IF(AND(I22="Low",J22="High"),"Develop / Grow","Review / Deprioritise"))) -> Reprice / Cost-to-Serve | L22: =IF(K22="Protect / Grow","Defend relationship and expand profitable volume",IF(K22="Reprice / Cost-to-Serve","Review discounts, freight and service economics",IF(K22="Develop / Grow","Target selective volume growth","Review account economics and strategic fit"))) -> Review discounts, freight and service economics
A23: C063 | B23: FamilyCare Wholesale 03 | C23: Wholesale | D23: Strategic | E23: 17977.78 | F23: 5949.2536 | G23: 0.33092259 | H23: 0.1993856 | I23: =IF(E23>=$B$7,"High","Low") -> High | J23: =IF(G23>=$B$8,"High","Low") -> Low | K23: =IF(AND(I23="High",J23="High"),"Protect / Grow",IF(AND(I23="High",J23="Low"),"Reprice / Cost-to-Serve",IF(AND(I23="Low",J23="High"),"Develop / Grow","Review / Deprioritise"))) -> Reprice / Cost-to-Serve | L23: =IF(K23="Protect / Grow","Defend relationship and expand profitable volume",IF(K23="Reprice / Cost-to-Serve","Review discounts, freight and service economics",IF(K23="Develop / Grow","Target selective volume growth","Review account economics and strategic fit"))) -> Review discounts, freight and service economics
... A101: C059 | B101: Direct Family Customer 14 | C101: DTC | D101: Long Tail | E101: 377.34381 | F101: 152.04334 | G101: 0.40293053 | H101: 0.063477082 | I101: =IF(E101>=$B$7,"High","Low") -> Low | J101: =IF(G101>=$B$8,"High","Low") -> High | K101: =IF(AND(I101="High",J101="High"),"Protect / Grow",IF(AND(I101="High",J101="Low"),"Reprice / Cost-to-Serve",IF(AND(I101="Low",J101="High"),"Develop / Grow","Review / Deprioritise"))) -> Develop / Grow | L101: =IF(K101="Protect / Grow","Defend relationship and expand profitable volume",IF(K101="Reprice / Cost-to-Serve","Review discounts, freight and service economics",IF(K101="Develop / Grow","Target selective volume growth","Review account economics and strategic fit"))) -> Target selective volume growth
A104: Quadrant summary
A105: Quadrant | B105: Customers | C105: Net Revenue (£) | D105: Contribution Profit (£)
A106: Protect / Grow | B106: =COUNTIF(K12:K101,A106) -> 21 | C106: =SUMIF(K12:K101,A106,E12:E101) -> 255252.25 | D106: =SUMIF(K12:K101,A106,F12:F101) -> 99169.457
A107: Reprice / Cost-to-Serve | B107: =COUNTIF(K12:K101,A107) -> 24 | C107: =SUMIF(K12:K101,A107,E12:E101) -> 298666.01 | D107: =SUMIF(K12:K101,A107,F12:F101) -> 103208.36
A108: Develop / Grow | B108: =COUNTIF(K12:K101,A108) -> 24 | C108: =SUMIF(K12:K101,A108,E12:E101) -> 35169.486 | D108: =SUMIF(K12:K101,A108,F12:F101) -> 13688.159
A109: Review / Deprioritise | B109: =COUNTIF(K12:K101,A109) -> 21 | C109: =SUMIF(K12:K101,A109,E12:E101) -> 43693.72 | D109: =SUMIF(K12:K101,A109,F12:F101) -> 14997.823

Sheet Pricing Waterfall
A1: Pricing & Margin Waterfall
A3: Commercial bridge from list-price gross sales to contribution profit. All figures are synthetic.
A5: Portfolio pricing waterfall
A6: Step | B6: Impact (£) | C6: Running Value (£) | E6: KPI | F6: Value
A7: Gross Sales | B7: 730829.56 | C7: 730829.56 | E7: Discount Rate | F7: 0.13415999
A8: Discounts | B8: -98048.089 | C8: 632781.47 | E8: Gross Margin | F8: 0.39434954
A9: Net Revenue | B9: 0 | C9: 632781.47 | E9: Contribution Margin | F9: 0.36515577
A10: COGS | B10: -383244.39 | C10: 249537.08 | E10: Cost-to-Serve % | F10: 0.029193772
A11: Gross Profit | B11: 0 | C11: 249537.08
A12: Freight | B12: -16258.148 | C12: 233278.93
A13: Promo Spend | B13: -2215.13 | C13: 231063.8
A14: Contribution Profit | B14: 0 | C14: 231063.8
A17: Waterfall by channel
A18: Channel | B18: Gross Sales (£) | C18: Discounts (£) | D18: Net Revenue (£) | E18: COGS (£) | F18: Gross Profit (£) | G18: Freight (£) | H18: Promo Spend (£) | I18: Contribution Profit (£) | J18: Contribution Margin
A19: DTC | B19: 138529.4 | C19: 10161.515 | D19: 128367.88 | E19: 72088.76 | F19: 56279.125 | G19: 5776.5548 | H19: 342.25 | I19: 50160.32 | J19: 0.39075443
A20: Baby Specialist | B20: 120644.91 | C20: 13422.029 | D20: 107222.88 | E20: 64006.94 | F20: 43215.941 | G20: 2466.1263 | H20: 322.29 | I20: 40427.525 | J20: 0.37704196
A21: Pharmacy | B21: 120588.67 | C21: 14666.024 | D21: 105922.65 | E21: 63056.27 | F21: 42866.376 | G21: 2224.3756 | H21: 274.8 | I21: 40367.201 | J21: 0.38110076
A22: Online Marketplace | B22: 126233.66 | C22: 21202.021 | D22: 105031.64 | E22: 66263.39 | F22: 38768.249 | G22: 2730.8226 | H22: 625.63 | I22: 35411.797 | J22: 0.33715361
A23: Wholesale | B23: 120203.06 | C23: 22874.096 | D23: 97328.964 | E23: 62803.15 | F23: 34525.814 | G23: 1459.9345 | H23: 247.65 | I23: 32818.23 | J23: 0.33718873
A24: Grocery | B24: 104629.86 | C24: 15722.405 | D24: 88907.455 | E24: 55025.88 | F24: 33881.575 | G24: 1600.3342 | H24: 402.51 | I24: 31878.731 | J24: 0.35856083

Sheet Promo Effectiveness
A1: Promotion Effectiveness & ROI Proxy
A3: ROI is an observational effectiveness proxy: actual promo contribution is compared with a non-promo transaction baseline. It is not a causal experiment.
A6: Category | B6: Promo Txns | C6: Non-Promo Txns | D6: Promo Units / Txn | E6: Non-Promo Units / Txn | F6: Unit Uplift % | G6: Promo Revenue (£) | H6: Promo Spend (£) | I6: Promo CM | J6: Non-Promo CM | K6: Incremental Contribution Proxy (£) | L6: ROI Proxy | M6: Assessment | O6: Category | P6: ROI Proxy
A7: Skincare | B7: 51 | C7: 227 | D7: 30.627451 | E7: 28.365639 | F7: 0.07973775 | G7: 11681.458 | H7: 221.48 | I7: 0.40395131 | J7: 0.43740949 | K7: 249.27851 | L7: 1.1255125 | M7: =IF(L7>=1,"Strong",IF(L7>0,"Marginal","Value destructive")) -> Strong | O7: Skincare | P7: 1.1255125
A8: Baby Bath | B8: 64 | C8: 275 | D8: 39.953125 | E8: 33.214545 | F8: 0.20288038 | G8: 13524.281 | H8: 296.88 | I8: 0.38568268 | J8: 0.432616 | K8: 237.25537 | L8: 0.79916251 | M8: =IF(L8>=1,"Strong",IF(L8>0,"Marginal","Value destructive")) -> Marginal | O8: Baby Bath | P8: 0.79916251
A9: Wipes | B9: 90 | C9: 386 | D9: 54.7 | E9: 51.774611 | F9: 0.056502377 | G9: 28377.894 | H9: 591.85 | I9: 0.32136176 | J9: 0.37167401 | K9: -872.20449 | L9: -1.4736918 | M9: =IF(L9>=1,"Strong",IF(L9>0,"Marginal","Value destructive")) -> Value destructive | O9: Wipes | P9: -1.4736918
A10: Feeding | B10: 36 | C10: 216 | D10: 26.111111 | E10: 23.574074 | F10: 0.1076198 | G10: 6256.1351 | H10: 121.25 | I10: 0.33118901 | J10: 0.39234774 | K10: -298.54171 | L10: -2.4621997 | M10: =IF(L10>=1,"Strong",IF(L10>0,"Marginal","Value destructive")) -> Value destructive | O10: Feeding | P10: -2.4621997
A11: Diapers | B11: 91 | C11: 425 | D11: 50.373626 | E11: 50.6 | F11: -0.0044737871 | G11: 47070.854 | H11: 927.61 | I11: 0.28825156 | J11: 0.35253271 | K11: -5400.6589 | L11: -5.8221224 | M11: =IF(L11>=1,"Strong",IF(L11>0,"Marginal","Value destructive")) -> Value destructive | O11: Diapers | P11: -5.8221224
A12: Nursery | B12: 18 | C12: 121 | D12: 9.8888889 | E12: 13.181818 | F12: -0.24980843 | G12: 2881.0272 | H12: 56.06 | I12: 0.29471335 | J12: 0.33977419 | K12: -425.1384 | L12: -7.5836319 | M12: =IF(L12>=1,"Strong",IF(L12>0,"Marginal","Value destructive")) -> Value destructive | O12: Nursery | P12: -7.5836319

Sheet Customer Concentration
A1: Customer Concentration & Pareto Analysis
A3: Concentration measures are based on synthetic net revenue. HHI is shown as a portfolio diagnostic, not a regulatory conclusion.
A5: Concentration KPIs
A6: Metric | B6: Value
A7: Largest Customer Share | B7: 0.046928608
A8: Top 5 Revenue Share | B8: 0.20018987
A9: Top 10 Revenue Share | B9: 0.36180563
A10: Revenue HHI | B10: 0.022997149
A13: Rank | B13: Customer ID | C13: Customer Name | D13: Channel | E13: Net Revenue (£) | F13: Revenue Share | G13: Cumulative Share | H13: Contribution Profit (£) | I13: Contribution Margin | K13: Rank | L13: Cumulative Share
A14: 1 | B14: C046 | C14: Direct Family Customer 01 | D14: DTC | E14: 29695.553 | F14: 0.046928608 | G14: 0.046928608 | H14: 11810.533 | I14: 0.39772061 | K14: 1 | L14: 0.046928608
A15: 2 | B15: C047 | C15: Direct Family Customer 02 | D15: DTC | E15: 28448.002 | F15: 0.044957072 | G15: 0.09188568 | H15: 10752.882 | I15: 0.37798374 | K15: 2 | L15: 0.09188568
A16: 3 | B16: C077 | C16: LittleNest Retail 02 | D16: Baby Specialist | E16: 23824.362 | F16: 0.037650221 | G16: 0.1295359 | H16: 8796.2518 | I16: 0.36921248 | K16: 3 | L16: 0.1295359
A17: 4 | B17: C001 | C17: Northgate Grocers 01 | D17: Grocery | E17: 23314.544 | F17: 0.036844543 | G17: 0.16638044 | H17: 8233.2724 | I17: 0.3531389 | K17: 4 | L17: 0.16638044
A18: 5 | B18: C031 | C18: HomeCart Online 01 | D18: Online Marketplace | E18: 21393.976 | F18: 0.033809422 | G18: 0.20018987 | H18: 7298.4322 | I18: 0.34114427 | K18: 5 | L18: 0.20018987
A19: 6 | B19: C033 | C19: HomeCart Online 03 | D19: Online Marketplace | E19: 21060.262 | F19: 0.033282047 | G19: 0.23347191 | H19: 6649.9756 | I19: 0.31575939 | K19: 6 | L19: 0.23347191
A20: 7 | B20: C048 | C20: Direct Family Customer 03 | D20: DTC | E20: 20694.212 | F20: 0.032703568 | G20: 0.26617548 | H20: 8075.2223 | I20: 0.39021647 | K20: 7 | L20: 0.26617548
A21: 8 | B21: C032 | C21: HomeCart Online 02 | D21: Online Marketplace | E21: 20627.807 | F21: 0.032598627 | G21: 0.29877411 | H21: 6834.6545 | I21: 0.33133209 | K21: 8 | L21: 0.29877411
A22: 9 | B22: C018 | C22: WellSpring Pharmacy 03 | D22: Pharmacy | E22: 20045.679 | F22: 0.031678675 | G22: 0.33045278 | H22: 7666.1395 | I22: 0.38243352 | K22: 9 | L22: 0.33045278
A23: 10 | B23: C078 | C23: LittleNest Retail 03 | D23: Baby Specialist | E23: 19839.5 | F23: 0.031352847 | G23: 0.36180563 | H23: 7453.0119 | I23: 0.3756653 | K23: 10 | L23: 0.36180563
A24: 11 | B24: C017 | C24: WellSpring Pharmacy 02 | D24: Pharmacy | E24: 19566.794 | F24: 0.030921882 | G24: 0.39272751 | H24: 7153.0515 | I24: 0.36557095 | K24: 11 | L24: 0.39272751
A25: 12 | B25: C063 | C25: FamilyCare Wholesale 03 | D25: Wholesale | E25: 17977.78 | F25: 0.028410725 | G25: 0.42113824 | H25: 5949.2536 | I25: 0.33092259 | K25: 12 | L25: 0.42113824
... A33: 20 | B33: C037 | C33: HomeCart Online 07 | D33: Online Marketplace | E33: 9511.5832 | F33: 0.015031387 | G33: 0.59800611 | H33: 3189.912 | I33: 0.3353713 | K33: 20 | L33: 0.59800611
A34: 21 | B34: C051 | C34: Direct Family Customer 06 | D34: DTC | E34: 9100.4231 | F34: 0.014381621 | G34: 0.61238773 | H34: 3581.4741 | I34: 0.39355028
A35: 22 | B35: C019 | C35: WellSpring Pharmacy 04 | D35: Pharmacy | E35: 8880.5484 | F35: 0.014034147 | G35: 0.62642188 | H35: 3230.1869 | I35: 0.36373732
A36: 23 | B36: C005 | C36: Northgate Grocers 05 | D36: Grocery | E36: 8163.7079 | F36: 0.012901307 | G36: 0.63932319 | H36: 2884.4512 | I36: 0.35332611
A37: 24 | B37: C064 | C37: FamilyCare Wholesale 04 | D37: Wholesale | E37: 8063.2647 | F37: 0.012742574 | G37: 0.65206576 | H37: 2954.4557 | I37: 0.36640937
A38: 25 | B38: C050 | C38: Direct Family Customer 05 | D38: DTC | E38: 7997.4103 | F38: 0.012638503 | G38: 0.66470426 | H38: 3019.1668 | I38: 0.37751806
A39: 26 | B39: C023 | C39: WellSpring Pharmacy 08 | D39: Pharmacy | E39: 7846.005 | F39: 0.012399233 | G39: 0.6771035 | H39: 2930.9489 | I39: 0.37355939
A40: 27 | B40: C004 | C40: Northgate Grocers 04 | D40: Grocery | E40: 7719.0378 | F40: 0.012198584 | G40: 0.68930208 | H40: 3083.5951 | I40: 0.39947921
A41: 28 | B41: C082 | C41: LittleNest Retail 07 | D41: Baby Specialist | E41: 7609.8479 | F41: 0.012026028 | G41: 0.70132811 | H41: 2938.7914 | I41: 0.38618268
A42: 29 | B42: C002 | C42: Northgate Grocers 02 | D42: Grocery | E42: 7430.5226 | F42: 0.011742636 | G42: 0.71307075 | H42: 2767.3832 | I42: 0.37243453
A43: 30 | B43: C020 | C43: WellSpring Pharmacy 05 | D43: Pharmacy | E43: 7397.3488 | F43: 0.011690211 | G43: 0.72476096 | H43: 2926.4745 | I43: 0.39561126
A44: 31 | B44: C052 | C44: Direct Family Customer 07 | D44: DTC | E44: 7139.0146 | F44: 0.011281959 | G44: 0.73604292 | H44: 2834.7189 | I44: 0.39707426
A45: 32 | B45: C036 | C45: HomeCart Online 06 | D45: Online Marketplace | E45: 7072.3424 | F45: 0.011176595 | G45: 0.74721951 | H45: 2633.9415 | I45: 0.37242845
... A103: 90 | B103: C059 | C103: Direct Family Customer 14 | D103: DTC | E103: 377.34381 | F103: 0.00059632564 | G103: 1 | H103: 152.04334 | I103: 0.40293053

Sheet SKU Rationalisation
A1: SKU Rationalisation & Portfolio Actions
A3: Quadrants use median SKU revenue and contribution margin. Actions are model recommendations for this synthetic case study.
A5: Portfolio thresholds
A6: Metric | B6: Threshold
A7: Median SKU Revenue | B7: 7278.8395
A8: Median Contribution Margin | B8: 0.38195237
A11: Product ID | B11: SKU Name | C11: Brand | D11: Category | E11: Net Revenue (£) | F11: Units | G11: ASP (£) | H11: Gross Profit (£) | I11: GP Margin | J11: Promo Spend (£) | K11: Contribution Profit (£) | L11: Contribution Margin | M11: Portfolio Action | N11: Commercial Recommendation
A12: P014 | B12: LittleBloom Diapers 40 pack | C12: LittleBloom | D12: Diapers | E12: 46531.071 | F12: 3428 | G12: 13.573825 | H12: 16855.561 | I12: 0.36224314 | J12: 132.99 | K12: 15517.582 | L12: 0.3334886 | M12: =IF(AND(E12>=$B$7,L12>=$B$8),"Protect / Grow",IF(AND(E12>=$B$7,L12<$B$8),"Reprice / Cost Action",IF(AND(E12<$B$7,L12>=$B$8),"Scale Selectively","Rationalise / Review"))) -> Reprice / Cost Action | N12: =IF(M12="Protect / Grow","Defend margin and expand profitable volume",IF(M12="Reprice / Cost Action","Review price, discount and direct costs",IF(M12="Scale Selectively","Test targeted distribution / volume growth","Review delisting, simplification or strategic role"))) -> Review price, discount and direct costs
A13: P038 | B13: TinySteps Diapers 40 pack | C13: TinySteps | D13: Diapers | E13: 37222.206 | F13: 2874 | G13: 12.951359 | H13: 10430.416 | I13: 0.28022025 | J13: 99.74 | K13: 9465.2546 | L13: 0.25429054 | M13: =IF(AND(E13>=$B$7,L13>=$B$8),"Protect / Grow",IF(AND(E13>=$B$7,L13<$B$8),"Reprice / Cost Action",IF(AND(E13<$B$7,L13>=$B$8),"Scale Selectively","Rationalise / Review"))) -> Reprice / Cost Action | N13: =IF(M13="Protect / Grow","Defend margin and expand profitable volume",IF(M13="Reprice / Cost Action","Review price, discount and direct costs",IF(M13="Scale Selectively","Test targeted distribution / volume growth","Review delisting, simplification or strategic role"))) -> Review price, discount and direct costs
A14: P002 | B14: Nurtura Diapers 40 pack | C14: Nurtura | D14: Diapers | E14: 36042.261 | F14: 2488 | G14: 14.486439 | H14: 14229.281 | I14: 0.39479435 | J14: 78.52 | K14: 13101.813 | L14: 0.36351253 | M14: =IF(AND(E14>=$B$7,L14>=$B$8),"Protect / Grow",IF(AND(E14>=$B$7,L14<$B$8),"Reprice / Cost Action",IF(AND(E14<$B$7,L14>=$B$8),"Scale Selectively","Rationalise / Review"))) -> Reprice / Cost Action | N14: =IF(M14="Protect / Grow","Defend margin and expand profitable volume",IF(M14="Reprice / Cost Action","Review price, discount and direct costs",IF(M14="Scale Selectively","Test targeted distribution / volume growth","Review delisting, simplification or strategic role"))) -> Review price, discount and direct costs
A15: P001 | B15: Nurtura Diapers 24 pack | C15: Nurtura | D15: Diapers | E15: 35430.984 | F15: 3864 | G15: 9.1695093 | H15: 13615.884 | I15: 0.38429314 | J15: 88.11 | K15: 12637.602 | L15: 0.35668221 | M15: =IF(AND(E15>=$B$7,L15>=$B$8),"Protect / Grow",IF(AND(E15>=$B$7,L15<$B$8),"Reprice / Cost Action",IF(AND(E15<$B$7,L15>=$B$8),"Scale Selectively","Rationalise / Review"))) -> Reprice / Cost Action | N15: =IF(M15="Protect / Grow","Defend margin and expand profitable volume",IF(M15="Reprice / Cost Action","Review price, discount and direct costs",IF(M15="Scale Selectively","Test targeted distribution / volume growth","Review delisting, simplification or strategic role"))) -> Review price, discount and direct costs
A16: P037 | B16: TinySteps Diapers 24 pack | C16: TinySteps | D16: Diapers | E16: 29819.922 | F16: 3574 | G16: 8.3435709 | H16: 9626.8724 | I16: 0.32283358 | J16: 159.65 | K16: 8651.1256 | L16: 0.29011228 | M16: =IF(AND(E16>=$B$7,L16>=$B$8),"Protect / Grow",IF(AND(E16>=$B$7,L16<$B$8),"Reprice / Cost Action",IF(AND(E16<$B$7,L16>=$B$8),"Scale Selectively","Rationalise / Review"))) -> Reprice / Cost Action | N16: =IF(M16="Protect / Grow","Defend margin and expand profitable volume",IF(M16="Reprice / Cost Action","Review price, discount and direct costs",IF(M16="Scale Selectively","Test targeted distribution / volume growth","Review delisting, simplification or strategic role"))) -> Review price, discount and direct costs
A17: P013 | B17: LittleBloom Diapers 24 pack | C17: LittleBloom | D17: Diapers | E17: 25714.647 | F17: 2908 | G17: 8.8427259 | H17: 8349.2168 | I17: 0.32468721 | J17: 99.21 | K17: 7615.2231 | L17: 0.29614341 | M17: =IF(AND(E17>=$B$7,L17>=$B$8),"Protect / Grow",IF(AND(E17>=$B$7,L17<$B$8),"Reprice / Cost Action",IF(AND(E17<$B$7,L17>=$B$8),"Scale Selectively","Rationalise / Review"))) -> Reprice / Cost Action | N17: =IF(M17="Protect / Grow","Defend margin and expand profitable volume",IF(M17="Reprice / Cost Action","Review price, discount and direct costs",IF(M17="Scale Selectively","Test targeted distribution / volume growth","Review delisting, simplification or strategic role"))) -> Review price, discount and direct costs
A18: P004 | B18: Nurtura Wipes 8 pack | C18: Nurtura | D18: Wipes | E18: 21286.101 | F18: 3057 | G18: 6.9630686 | H18: 8539.6506 | I18: 0.40118436 | J18: 111.79 | K18: 7956.8931 | L18: 0.37380699 | M18: =IF(AND(E18>=$B$7,L18>=$B$8),"Protect / Grow",IF(AND(E18>=$B$7,L18<$B$8),"Reprice / Cost Action",IF(AND(E18<$B$7,L18>=$B$8),"Scale Selectively","Rationalise / Review"))) -> Reprice / Cost Action | N18: =IF(M18="Protect / Grow","Defend margin and expand profitable volume",IF(M18="Reprice / Cost Action","Review price, discount and direct costs",IF(M18="Scale Selectively","Test targeted distribution / volume growth","Review delisting, simplification or strategic role"))) -> Review price, discount and direct costs
A19: P040 | B19: TinySteps Wipes 8 pack | C19: TinySteps | D19: Wipes | E19: 17706.117 | F19: 2771 | G19: 6.3897933 | H19: 5672.3672 | I19: 0.32036201 | J19: 91.36 | K19: 5126.2958 | L19: 0.28952117 | M19: =IF(AND(E19>=$B$7,L19>=$B$8),"Protect / Grow",IF(AND(E19>=$B$7,L19<$B$8),"Reprice / Cost Action",IF(AND(E19<$B$7,L19>=$B$8),"Scale Selectively","Rationalise / Review"))) -> Reprice / Cost Action | N19: =IF(M19="Protect / Grow","Defend margin and expand profitable volume",IF(M19="Reprice / Cost Action","Review price, discount and direct costs",IF(M19="Scale Selectively","Test targeted distribution / volume growth","Review delisting, simplification or strategic role"))) -> Review price, discount and direct costs
A20: P003 | B20: Nurtura Wipes 4 pack | C20: Nurtura | D20: Wipes | E20: 17000.325 | F20: 3687 | G20: 4.6108828 | H20: 6676.915 | I20: 0.3927522 | J20: 18.68 | K20: 6205.3868 | L20: 0.36501577 | M20: =IF(AND(E20>=$B$7,L20>=$B$8),"Protect / Grow",IF(AND(E20>=$B$7,L20<$B$8),"Reprice / Cost Action",IF(AND(E20<$B$7,L20>=$B$8),"Scale Selectively","Rationalise / Review"))) -> Reprice / Cost Action | N20: =IF(M20="Protect / Grow","Defend margin and expand profitable volume",IF(M20="Reprice / Cost Action","Review price, discount and direct costs",IF(M20="Scale Selectively","Test targeted distribution / volume growth","Review delisting, simplification or strategic role"))) -> Review price, discount and direct costs
A21: P016 | B21: LittleBloom Wipes 8 pack | C21: LittleBloom | D21: Wipes | E21: 15940.315 | F21: 2395 | G21: 6.6556638 | H21: 5979.0549 | I21: 0.37509014 | J21: 37.63 | K21: 5554.9735 | L21: 0.34848581 | M21: =IF(AND(E21>=$B$7,L21>=$B$8),"Protect / Grow",IF(AND(E21>=$B$7,L21<$B$8),"Reprice / Cost Action",IF(AND(E21<$B$7,L21>=$B$8),"Scale Selectively","Rationalise / Review"))) -> Reprice / Cost Action | N21: =IF(M21="Protect / Grow","Defend margin and expand profitable volume",IF(M21="Reprice / Cost Action","Review price, discount and direct costs",IF(M21="Scale Selectively","Test targeted distribution / volume growth","Review delisting, simplification or strategic role"))) -> Review price, discount and direct costs
A22: P039 | B22: TinySteps Wipes 4 pack | C22: TinySteps | D22: Wipes | E22: 13345.645 | F22: 3265 | G22: 4.0874869 | H22: 4724.1646 | I22: 0.3539855 | J22: 63.04 | K22: 4318.1644 | L22: 0.32356357 | M22: =IF(AND(E22>=$B$7,L22>=$B$8),"Protect / Grow",IF(AND(E22>=$B$7,L22<$B$8),"Reprice / Cost Action",IF(AND(E22<$B$7,L22>=$B$8),"Scale Selectively","Rationalise / Review"))) -> Reprice / Cost Action | N22: =IF(M22="Protect / Grow","Defend margin and expand profitable volume",IF(M22="Reprice / Cost Action","Review price, discount and direct costs",IF(M22="Scale Selectively","Test targeted distribution / volume growth","Review delisting, simplification or strategic role"))) -> Review price, discount and direct costs
A23: P015 | B23: LittleBloom Wipes 4 pack | C23: LittleBloom | D23: Wipes | E23: 12027.201 | F23: 2770 | G23: 4.3419499 | H23: 4349.7413 | I23: 0.36165864 | J23: 43.4 | K23: 3982.6702 | L23: 0.33113857 | M23: =IF(AND(E23>=$B$7,L23>=$B$8),"Protect / Grow",IF(AND(E23>=$B$7,L23<$B$8),"Reprice / Cost Action",IF(AND(E23<$B$7,L23>=$B$8),"Scale Selectively","Rationalise / Review"))) -> Reprice / Cost Action | N23: =IF(M23="Protect / Grow","Defend margin and expand profitable volume",IF(M23="Reprice / Cost Action","Review price, discount and direct costs",IF(M23="Scale Selectively","Test targeted distribution / volume growth","Review delisting, simplification or strategic role"))) -> Review price, discount and direct costs
... A59: P035 | B59: PureNest Nursery Single | C59: PureNest | D59: Nursery | E59: 2079.1758 | F59: 152 | G59: 13.678788 | H59: 852.44578 | I59: 0.40999216 | J59: 7.34 | K59: 798.58327 | L59: 0.38408646 | M59: =IF(AND(E59>=$B$7,L59>=$B$8),"Protect / Grow",IF(AND(E59>=$B$7,L59<$B$8),"Reprice / Cost Action",IF(AND(E59<$B$7,L59>=$B$8),"Scale Selectively","Rationalise / Review"))) -> Scale Selectively | N59: =IF(M59="Protect / Grow","Defend margin and expand profitable volume",IF(M59="Reprice / Cost Action","Review price, discount and direct costs",IF(M59="Scale Selectively","Test targeted distribution / volume growth","Review delisting, simplification or strategic role"))) -> Test targeted distribution / volume growth
A62: Portfolio action summary
A63: Action | B63: SKUs | C63: Net Revenue (£) | D63: Contribution Profit (£)
A64: Protect / Grow | B64: =COUNTIF(M12:M59,A64) -> 11 | C64: =SUMIF(M12:M59,A64,E12:E59) -> 203203.05 | D64: =SUMIF(M12:M59,A64,K12:K59) -> 84316.802
A65: Reprice / Cost Action | B65: =COUNTIF(M12:M59,A65) -> 13 | C65: =SUMIF(M12:M59,A65,E12:E59) -> 316883.55 | D65: =SUMIF(M12:M59,A65,K12:K59) -> 103481.75
A66: Scale Selectively | B66: =COUNTIF(M12:M59,A66) -> 13 | C66: =SUMIF(M12:M59,A66,E12:E59) -> 66687.415 | D66: =SUMIF(M12:M59,A66,K12:K59) -> 27975.951
A67: Rationalise / Review | B67: =COUNTIF(M12:M59,A67) -> 11 | C67: =SUMIF(M12:M59,A67,E12:E59) -> 46007.454 | D67: =SUMIF(M12:M59,A67,K12:K59) -> 15289.3

Sheet PVM Analysis V2
A1: Price–Volume–Mix — Jan–Sep 2025 vs Jan–Sep 2026
A3: Like-for-like YTD comparison using category-level mix. Bridge reconciles current-year revenue growth into volume, mix and price.
A5: Category | B5: 2025 Units | C5: 2026 Units | D5: 2025 Mix % | E5: 2026 Mix % | F5: 2025 ASP (£) | G5: 2026 ASP (£) | H5: Volume Effect (£) | I5: Mix Effect (£) | J5: Price Effect (£) | K5: PVM Total (£) | L5: Revenue Variance (£) | M5: Control (£)
A6: Diapers | B6: 10545 | C6: 11068 | D6: =B6/$B$12 -> 0.32959305 | E6: =C6/$C$12 -> 0.33496762 | F6: 11.205567 | G6: 11.652553 | H6: =($C$12-$B$12)*D6*F6 -> 3870.5543 | I6: =$C$12*(E6-D6)*F6 -> 1989.9573 | J6: =C6*(G6-F6) -> 4947.2425 | K6: =H6+I6+J6 -> 10807.754 | L6: 10807.754 | M6: =K6-L6 -> 0
A7: Wipes | B7: 9615 | C7: 10629 | D7: =B7/$B$12 -> 0.3005251 | E7: =C7/$C$12 -> 0.3216815 | F7: 5.7123079 | G7: 5.9591819 | H7: =($C$12-$B$12)*D7*F7 -> 1799.0931 | I7: =$C$12*(E7-D7)*F7 -> 3993.1871 | J7: =C7*(G7-F7) -> 2624.0244 | K7: =H7+I7+J7 -> 8416.3046 | L7: 8416.3046 | M7: =K7-L7 -> 0
A8: Baby Bath | B8: 4880 | C8: 4982 | D8: =B8/$B$12 -> 0.1525286 | E8: =C8/$C$12 -> 0.1507778 | F8: 5.2496126 | G8: 5.508644 | H8: =($C$12-$B$12)*D8*F8 -> 839.15043 | I8: =$C$12*(E8-D8)*F8 -> -303.68994 | J8: =C8*(G8-F8) -> 1290.4945 | K8: =H8+I8+J8 -> 1825.9549 | L8: 1825.9549 | M8: =K8-L8 -> -4.5474735e-12
A9: Skincare | B9: 3758 | C9: 2956 | D9: =B9/$B$12 -> 0.11745952 | E9: =C9/$C$12 -> 0.089461897 | F9: 6.9760343 | G9: 7.2562681 | H9: =($C$12-$B$12)*D9*F9 -> 858.73295 | I9: =$C$12*(E9-D9)*F9 -> -6453.5125 | J9: =C9*(G9-F9) -> 828.37092 | K9: =H9+I9+J9 -> -4766.4086 | L9: -4766.4086 | M9: =K9-L9 -> 0
A10: Feeding | B10: 2287 | C10: 2744 | D10: =B10/$B$12 -> 0.071482153 | E10: =C10/$C$12 -> 0.08304582 | F10: 6.9935377 | G10: 7.0817673 | H10: =($C$12-$B$12)*D10*F10 -> 523.90896 | I10: =$C$12*(E10-D10)*F10 -> 2672.1377 | J10: =C10*(G10-F10) -> 242.10211 | K10: =H10+I10+J10 -> 3438.1488 | L10: 3438.1488 | M10: =K10-L10 -> 0
A11: Nursery | B11: 909 | C11: 663 | D11: =B11/$B$12 -> 0.028411577 | E11: =C11/$C$12 -> 0.020065371 | F11: 14.95878 | G11: 17.225489 | H11: =($C$12-$B$12)*D11*F11 -> 445.40266 | I11: =$C$12*(E11-D11)*F11 -> -4125.2626 | J11: =C11*(G11-F11) -> 1502.828 | K11: =H11+I11+J11 -> -2177.0319 | L11: -2177.0319 | M11: =K11-L11 -> 3.6379788e-12
A12: TOTAL | B12: 31994 | C12: 33042 | D12: =SUM(D6:D11) -> 1 | E12: =SUM(E6:E11) -> 1 | F12: =SUMPRODUCT(B6:B11,F6:F11)/B12 -> 7.9550023 | G12: =SUMPRODUCT(C6:C11,G6:G11)/C12 -> 8.2336742 | H12: =SUM(H6:H11) -> 8336.8424 | I12: =SUM(I6:I11) -> -2227.183 | J12: =SUM(J6:J11) -> 11435.062 | K12: =SUM(K6:K11) -> 17544.722 | L12: 17544.722 | M12: =K12-L12 -> 0
A15: Executive PVM bridge (£)
A16: Driver | B16: Effect
A17: Volume | B17: =H12 -> 8336.8424
A18: Mix | B18: =I12 -> -2227.183
A19: Price | B19: =J12 -> 11435.062
A20: Net Revenue Change | B20: =L12 -> 17544.722

Sheet Commercial Actions
A1: Commercial Finance Action Plan
A3: Decision-oriented summary linking pricing, customer, promo and SKU analytics to quantified actions.
A5: Priority repricing opportunities
A6: Priority | B6: Customer | C6: Channel | D6: Actual Discount | E6: Target Discount | F6: Potential Recapture (£) | G6: Recommended Action
A7: 1 | B7: Northgate Grocers 01 | C7: Grocery | D7: 0.16467481 | E7: 0.14502134 | F7: 383.97994 | G7: Reprice / renegotiate discount architecture
A8: 2 | B8: FamilyCare Wholesale 01 | C8: Wholesale | D8: 0.2090308 | E8: 0.18605435 | F8: 339.88501 | G8: Reprice / renegotiate discount architecture
A9: 3 | B9: FamilyCare Wholesale 03 | C9: Wholesale | D9: 0.1993856 | E9: 0.18140867 | F9: 282.57018 | G9: Reprice / renegotiate discount architecture
A10: 4 | B10: HomeCart Online 03 | C10: Online Marketplace | D10: 0.179612 | E10: 0.165361 | F10: 256.08718 | G10: Reprice / renegotiate discount architecture
A11: 5 | B11: Direct Family Customer 02 | C11: DTC | D11: 0.081698949 | E11: 0.071890251 | F11: 212.70422 | G11: Reprice / renegotiate discount architecture
A14: Promotion priorities | H14: SKU portfolio priorities
A15: Category | B15: ROI Proxy | C15: Promo CM | D15: Non-Promo CM | E15: Management View | H15: SKU | I15: Category | J15: Revenue (£) | K15: Contribution Margin | L15: Portfolio Action | M15: Recommendation | N15: Source
A16: Skincare | B16: 1.1255125 | C16: 0.40395131 | D16: 0.43740949 | E16: Scale / test further | H16: LittleBloom Diapers 40 pack | I16: Diapers | J16: 46531.071 | K16: 0.3334886 | L16: Reprice / Cost Action | M16: Review price / cost | N16: SQL / V2 model
A17: Baby Bath | B17: 0.79916251 | C17: 0.38568268 | D17: 0.432616 | E17: Review mechanics | H17: TinySteps Diapers 40 pack | I17: Diapers | J17: 37222.206 | K17: 0.25429054 | L17: Reprice / Cost Action | M17: Review price / cost | N17: SQL / V2 model
A18: Wipes | B18: -1.4736918 | C18: 0.32136176 | D18: 0.37167401 | E18: Redesign or stop | H18: Nurtura Diapers 40 pack | I18: Diapers | J18: 36042.261 | K18: 0.36351253 | L18: Reprice / Cost Action | M18: Review price / cost | N18: SQL / V2 model
A19: Feeding | B19: -2.4621997 | C19: 0.33118901 | D19: 0.39234774 | E19: Redesign or stop | H19: Nurtura Diapers 24 pack | I19: Diapers | J19: 35430.984 | K19: 0.35668221 | L19: Reprice / Cost Action | M19: Review price / cost | N19: SQL / V2 model
A20: Diapers | B20: -5.8221224 | C20: 0.28825156 | D20: 0.35253271 | E20: Redesign or stop | H20: TinySteps Diapers 24 pack | I20: Diapers | J20: 29819.922 | K20: 0.29011228 | L20: Reprice / Cost Action | M20: Review price / cost | N20: SQL / V2 model
A21: Nursery | B21: -7.5836319 | C21: 0.29471335 | D21: 0.33977419 | E21: Redesign or stop | H21: LittleBloom Diapers 24 pack | I21: Diapers | J21: 25714.647 | K21: 0.29614341 | L21: Reprice / Cost Action | M21: Review price / cost | N21: SQL / V2 model
H22: Nurtura Wipes 8 pack | I22: Wipes | J22: 21286.101 | K22: 0.37380699 | L22: Reprice / Cost Action | M22: Review price / cost | N22: SQL / V2 model
H23: TinySteps Wipes 8 pack | I23: Wipes | J23: 17706.117 | K23: 0.28952117 | L23: Reprice / Cost Action | M23: Review price / cost | N23: SQL / V2 model
A25: Management conclusions
A26: ="The model identifies £"&ROUND('Discount Leakage'!B102,0)&" of potential discount recapture under the 70% realisation assumption. "&"Top-10 customers represent "&ROUND('Customer Concentration'!B9*100,1)&"% of portfolio revenue. "&"Jan–Sep 2026 revenue increased by £"&ROUND('PVM Analysis V2'!L12,0)&", driven by volume £"&ROUND('PVM Analysis V2'!H12,0)&", mix £"&ROUND('PVM Analysis V2'!I12,0)&" and price £"&ROUND('PVM Analysis V2'!J12,0)&". "&"Commercial priorities are to protect high-margin growth accounts, reprice structurally over-discounted customers, redesign negative-ROI promotions and review low-revenue/low-margin SKUs." -> The model identifies £3875 of potential discount recapture under the 70% realisation assumption. Top-10 customers represent 36.2% of portfolio revenue. Jan–Sep 2026 revenue increased by £17545, driven by volume £8337, mix £-2227 and price £11435. Commercial priorities are to protect high-margin growth accounts, reprice structurally over-discounted customers, redesign negative-ROI promotions and review low-revenue/low-margin SKUs.

Sheet Commercial Dashboard V2
A1: Commercial Finance Dashboard V2 — Decision Support
A3: Pricing governance | customer economics | promo effectiveness | portfolio mix | Jan-2025 to Sep-2026
A5: Potential Discount Recapture | D5: Top 10 Customer Share | G5: 2026 YTD Revenue Change | J5: Price Effect
A6: ='Discount Leakage'!B102 -> 3875.371 | D6: ='Customer Concentration'!B9 -> 0.36180563 | G6: ='PVM Analysis V2'!L12 -> 17544.722 | J6: ='PVM Analysis V2'!J12 -> 11435.062
A9: Volume Effect | D9: Mix Effect | G9: Priority Repricing Accounts | J9: Weak Promo Categories
A10: ='PVM Analysis V2'!H12 -> 8336.8424 | D10: ='PVM Analysis V2'!I12 -> -2227.183 | G10: ='Discount Leakage'!B103 -> 11 | J10: =COUNTIF('Promo Effectiveness'!M7:M12,"Value destructive") -> 4
A14: Top Repricing Opportunities
A15: Customer | B15: Potential Recapture (£)
A16: Northgate Grocers 01 | B16: 383.97994
A17: FamilyCare Wholesale 01 | B17: 339.88501
A18: FamilyCare Wholesale 03 | B18: 282.57018
A19: HomeCart Online 03 | B19: 256.08718
A20: Direct Family Customer 02 | B20: 212.70422
A21: WellSpring Pharmacy 03 | B21: 173.37141
A22: LittleNest Retail 02 | B22: 163.95908
A23: HomeCart Online 02 | B23: 144.53471
A24: FamilyCare Wholesale 02 | B24: 127.50924
A25: Direct Family Customer 03 | B25: 115.14717
A32: Promotion ROI Proxy | I32: PVM Revenue Growth Drivers
A33: Category | B33: ROI Proxy | I33: Driver | J33: Effect (£)
A34: Skincare | B34: 1.1255125 | I34: Volume | J34: ='PVM Analysis V2'!H12 -> 8336.8424
A35: Baby Bath | B35: 0.79916251 | I35: Mix | J35: ='PVM Analysis V2'!I12 -> -2227.183
A36: Wipes | B36: -1.4736918 | I36: Price | J36: ='PVM Analysis V2'!J12 -> 11435.062
A37: Feeding | B37: -2.4621997
A38: Diapers | B38: -5.8221224
A39: Nursery | B39: -7.5836319
A52: Commercial management takeaways
A53: 1 | B53: Repricing: focus first on customers with structurally high effective discounts versus channel/tier policy.
A54: 2 | B54: Customer economics: grow high-revenue/high-margin accounts while separating revenue size from contribution quality.
A55: 3 | B55: Promotions: treat negative ROI proxies as a trigger for redesign/testing rather than assuming promotions create value.
A56: 4 | B56: Portfolio: protect high-revenue/high-margin SKUs; reprice high-revenue/low-margin SKUs; review low-revenue/low-margin tail.
A57: 5 | B57: Growth bridge: use PVM to distinguish genuine price realisation from volume and mix effects.

Sheet Pricing Scenarios
A1: Customer Repricing Scenario Model
A3: Scenario model converts discount leakage into a risk-adjusted contribution opportunity. It is a planning tool—not a realised saving or a causal demand forecast.
A5: Scenario controls | F5: Active assumptions
A6: Scenario | B6: Excess Discount Recovery | C6: Volume Retention | D6: Interpretation | F6: Metric | G6: Value | H6: Source
A7: Conservative | B7: 0.4 | C7: 0.995 | D7: Partial repricing with very high retention | F7: Recovery % | G7: =IF($B$10="Conservative",$B$7,IF($B$10="Stretch",$B$9,$B$8)) -> 0.7 | H7: Selected scenario
A8: Base | B8: 0.7 | C8: 0.99 | D8: Balanced repricing with limited attrition | F8: Volume Retention % | G8: =IF($B$10="Conservative",$C$7,IF($B$10="Stretch",$C$9,$C$8)) -> 0.99 | H8: Selected scenario
A9: Stretch | B9: 0.9 | C9: 0.98 | D9: Aggressive recovery with higher attrition risk
A10: Selected Scenario | B10: Base | D10: Editable scenario selector
A13: Risk-adjusted repricing economics — top 20 accounts
A14: Rank | B14: Customer | C14: Channel | D14: Tier | E14: Gross Sales (£) | F14: Net Revenue (£) | G14: Contribution Profit (£) | H14: Actual Discount % | I14: Target Discount % | J14: Excess Discount % | K14: Gross Leakage (£) | L14: Recovery % | M14: Volume Retention % | N14: Price Recapture on Retained Business (£) | O14: Contribution Lost from Attrition (£) | P14: Net Contribution Uplift (£) | Q14: Decision
A15: =1 -> 1 | B15: ='Discount Leakage'!B6 -> Northgate Grocers 01 | C15: ='Discount Leakage'!C6 -> Grocery | D15: ='Discount Leakage'!D6 -> Strategic | E15: ='Discount Leakage'!E6 -> 27910.74 | F15: ='Discount Leakage'!E6*(1-'Discount Leakage'!F6) -> 23314.544 | G15: =SUMIF('Customer Matrix'!$B$12:$B$101,B15,'Customer Matrix'!$F$12:$F$101) -> 8233.2724 | H15: ='Discount Leakage'!F6 -> 0.16467481 | I15: ='Discount Leakage'!K6 -> 0.14502134 | J15: ='Discount Leakage'!L6 -> 0.019653466 | K15: ='Discount Leakage'!M6 -> 548.54277 | L15: =$G$7 -> 0.7 | M15: =$G$8 -> 0.99 | N15: =K15*L15*M15 -> 380.14014 | O15: =G15*(1-M15) -> 82.332724 | P15: =N15-O15 -> 297.80741 | Q15: =IF(P15>=100,"Priority",IF(P15>0,"Selective","Do not reprice")) -> Priority
A16: =2 -> 2 | B16: ='Discount Leakage'!B7 -> FamilyCare Wholesale 01 | C16: ='Discount Leakage'!C7 -> Wholesale | D16: ='Discount Leakage'!D7 -> Strategic | E16: ='Discount Leakage'!E7 -> 21132.51 | F16: ='Discount Leakage'!E7*(1-'Discount Leakage'!F7) -> 16715.165 | G16: =SUMIF('Customer Matrix'!$B$12:$B$101,B16,'Customer Matrix'!$F$12:$F$101) -> 5674.6571 | H16: ='Discount Leakage'!F7 -> 0.2090308 | I16: ='Discount Leakage'!K7 -> 0.18605435 | J16: ='Discount Leakage'!L7 -> 0.022976448 | K16: ='Discount Leakage'!M7 -> 485.55001 | L16: =$G$7 -> 0.7 | M16: =$G$8 -> 0.99 | N16: =K16*L16*M16 -> 336.48616 | O16: =G16*(1-M16) -> 56.746571 | P16: =N16-O16 -> 279.73958 | Q16: =IF(P16>=100,"Priority",IF(P16>0,"Selective","Do not reprice")) -> Priority
A17: =3 -> 3 | B17: ='Discount Leakage'!B8 -> FamilyCare Wholesale 03 | C17: ='Discount Leakage'!C8 -> Wholesale | D17: ='Discount Leakage'!D8 -> Strategic | E17: ='Discount Leakage'!E8 -> 22454.98 | F17: ='Discount Leakage'!E8*(1-'Discount Leakage'!F8) -> 17977.78 | G17: =SUMIF('Customer Matrix'!$B$12:$B$101,B17,'Customer Matrix'!$F$12:$F$101) -> 5949.2536 | H17: ='Discount Leakage'!F8 -> 0.1993856 | I17: ='Discount Leakage'!K8 -> 0.18140867 | J17: ='Discount Leakage'!L8 -> 0.017976934 | K17: ='Discount Leakage'!M8 -> 403.67168 | L17: =$G$7 -> 0.7 | M17: =$G$8 -> 0.99 | N17: =K17*L17*M17 -> 279.74448 | O17: =G17*(1-M17) -> 59.492536 | P17: =N17-O17 -> 220.25194 | Q17: =IF(P17>=100,"Priority",IF(P17>0,"Selective","Do not reprice")) -> Priority
A18: =4 -> 4 | B18: ='Discount Leakage'!B9 -> HomeCart Online 03 | C18: ='Discount Leakage'!C9 -> Online Marketplace | D18: ='Discount Leakage'!D9 -> Strategic | E18: ='Discount Leakage'!E9 -> 25671.1 | F18: ='Discount Leakage'!E9*(1-'Discount Leakage'!F9) -> 21060.262 | G18: =SUMIF('Customer Matrix'!$B$12:$B$101,B18,'Customer Matrix'!$F$12:$F$101) -> 6649.9756 | H18: ='Discount Leakage'!F9 -> 0.179612 | I18: ='Discount Leakage'!K9 -> 0.165361 | J18: ='Discount Leakage'!L9 -> 0.014250999 | K18: ='Discount Leakage'!M9 -> 365.83883 | L18: =$G$7 -> 0.7 | M18: =$G$8 -> 0.99 | N18: =K18*L18*M18 -> 253.52631 | O18: =G18*(1-M18) -> 66.499756 | P18: =N18-O18 -> 187.02655 | Q18: =IF(P18>=100,"Priority",IF(P18>0,"Selective","Do not reprice")) -> Priority
A19: =5 -> 5 | B19: ='Discount Leakage'!B10 -> Direct Family Customer 02 | C19: ='Discount Leakage'!C10 -> DTC | D19: ='Discount Leakage'!D10 -> Strategic | E19: ='Discount Leakage'!E10 -> 30978.95 | F19: ='Discount Leakage'!E10*(1-'Discount Leakage'!F10) -> 28448.002 | G19: =SUMIF('Customer Matrix'!$B$12:$B$101,B19,'Customer Matrix'!$F$12:$F$101) -> 10752.882 | H19: ='Discount Leakage'!F10 -> 0.081698949 | I19: ='Discount Leakage'!K10 -> 0.071890251 | J19: ='Discount Leakage'!L10 -> 0.0098086982 | K19: ='Discount Leakage'!M10 -> 303.86317 | L19: =$G$7 -> 0.7 | M19: =$G$8 -> 0.99 | N19: =K19*L19*M19 -> 210.57718 | O19: =G19*(1-M19) -> 107.52882 | P19: =N19-O19 -> 103.04836 | Q19: =IF(P19>=100,"Priority",IF(P19>0,"Selective","Do not reprice")) -> Priority
A20: =6 -> 6 | B20: ='Discount Leakage'!B11 -> WellSpring Pharmacy 03 | C20: ='Discount Leakage'!C11 -> Pharmacy | D20: ='Discount Leakage'!D11 -> Strategic | E20: ='Discount Leakage'!E11 -> 23191.93 | F20: ='Discount Leakage'!E11*(1-'Discount Leakage'!F11) -> 20045.679 | G20: =SUMIF('Customer Matrix'!$B$12:$B$101,B20,'Customer Matrix'!$F$12:$F$101) -> 7666.1395 | H20: ='Discount Leakage'!F11 -> 0.13566147 | I20: ='Discount Leakage'!K11 -> 0.12498217 | J20: ='Discount Leakage'!L11 -> 0.010679294 | K20: ='Discount Leakage'!M11 -> 247.67345 | L20: =$G$7 -> 0.7 | M20: =$G$8 -> 0.99 | N20: =K20*L20*M20 -> 171.6377 | O20: =G20*(1-M20) -> 76.661395 | P20: =N20-O20 -> 94.976303 | Q20: =IF(P20>=100,"Priority",IF(P20>0,"Selective","Do not reprice")) -> Selective
A21: =7 -> 7 | B21: ='Discount Leakage'!B12 -> LittleNest Retail 02 | C21: ='Discount Leakage'!C12 -> Baby Specialist | D21: ='Discount Leakage'!D12 -> Strategic | E21: ='Discount Leakage'!E12 -> 27183.76 | F21: ='Discount Leakage'!E12*(1-'Discount Leakage'!F12) -> 23824.362 | G21: =SUMIF('Customer Matrix'!$B$12:$B$101,B21,'Customer Matrix'!$F$12:$F$101) -> 8796.2518 | H21: ='Discount Leakage'!F12 -> 0.12358106 | I21: ='Discount Leakage'!K12 -> 0.11496462 | J21: ='Discount Leakage'!L12 -> 0.0086164408 | K21: ='Discount Leakage'!M12 -> 234.22726 | L21: =$G$7 -> 0.7 | M21: =$G$8 -> 0.99 | N21: =K21*L21*M21 -> 162.31949 | O21: =G21*(1-M21) -> 87.962518 | P21: =N21-O21 -> 74.356972 | Q21: =IF(P21>=100,"Priority",IF(P21>0,"Selective","Do not reprice")) -> Selective
A22: =8 -> 8 | B22: ='Discount Leakage'!B13 -> HomeCart Online 02 | C22: ='Discount Leakage'!C13 -> Online Marketplace | D22: ='Discount Leakage'!D13 -> Strategic | E22: ='Discount Leakage'!E13 -> 24910.76 | F22: ='Discount Leakage'!E13*(1-'Discount Leakage'!F13) -> 20627.807 | G22: =SUMIF('Customer Matrix'!$B$12:$B$101,B22,'Customer Matrix'!$F$12:$F$101) -> 6834.6545 | H22: ='Discount Leakage'!F13 -> 0.17193183 | I22: ='Discount Leakage'!K13 -> 0.16364312 | J22: ='Discount Leakage'!L13 -> 0.0082887136 | K22: ='Discount Leakage'!M13 -> 206.47815 | L22: =$G$7 -> 0.7 | M22: =$G$8 -> 0.99 | N22: =K22*L22*M22 -> 143.08936 | O22: =G22*(1-M22) -> 68.346545 | P22: =N22-O22 -> 74.742817 | Q22: =IF(P22>=100,"Priority",IF(P22>0,"Selective","Do not reprice")) -> Selective
A23: =9 -> 9 | B23: ='Discount Leakage'!B14 -> FamilyCare Wholesale 02 | C23: ='Discount Leakage'!C14 -> Wholesale | D23: ='Discount Leakage'!D14 -> Strategic | E23: ='Discount Leakage'!E14 -> 19253.07 | F23: ='Discount Leakage'!E14*(1-'Discount Leakage'!F14) -> 15578.153 | G23: =SUMIF('Customer Matrix'!$B$12:$B$101,B23,'Customer Matrix'!$F$12:$F$101) -> 4802.4203 | H23: ='Discount Leakage'!F14 -> 0.19087436 | I23: ='Discount Leakage'!K14 -> 0.18141322 | J23: ='Discount Leakage'!L14 -> 0.0094611437 | K23: ='Discount Leakage'!M14 -> 182.15606 | L23: =$G$7 -> 0.7 | M23: =$G$8 -> 0.99 | N23: =K23*L23*M23 -> 126.23415 | O23: =G23*(1-M23) -> 48.024203 | P23: =N23-O23 -> 78.209948 | Q23: =IF(P23>=100,"Priority",IF(P23>0,"Selective","Do not reprice")) -> Selective
A24: =10 -> 10 | B24: ='Discount Leakage'!B15 -> Direct Family Customer 03 | C24: ='Discount Leakage'!C15 -> DTC | D24: ='Discount Leakage'!D15 -> Strategic | E24: ='Discount Leakage'!E15 -> 22586 | F24: ='Discount Leakage'!E15*(1-'Discount Leakage'!F15) -> 20694.212 | G24: =SUMIF('Customer Matrix'!$B$12:$B$101,B24,'Customer Matrix'!$F$12:$F$101) -> 8075.2223 | H24: ='Discount Leakage'!F15 -> 0.083759327 | I24: ='Discount Leakage'!K15 -> 0.076476233 | J24: ='Discount Leakage'!L15 -> 0.0072830935 | K24: ='Discount Leakage'!M15 -> 164.49595 | L24: =$G$7 -> 0.7 | M24: =$G$8 -> 0.99 | N24: =K24*L24*M24 -> 113.99569 | O24: =G24*(1-M24) -> 80.752223 | P24: =N24-O24 -> 33.24347 | Q24: =IF(P24>=100,"Priority",IF(P24>0,"Selective","Do not reprice")) -> Selective
A25: =11 -> 11 | B25: ='Discount Leakage'!B16 -> WellSpring Pharmacy 01 | C25: ='Discount Leakage'!C16 -> Pharmacy | D25: ='Discount Leakage'!D16 -> Strategic | E25: ='Discount Leakage'!E16 -> 19627.16 | F25: ='Discount Leakage'!E16*(1-'Discount Leakage'!F16) -> 17060.866 | G25: =SUMIF('Customer Matrix'!$B$12:$B$101,B25,'Customer Matrix'!$F$12:$F$101) -> 6722.8478 | H25: ='Discount Leakage'!F16 -> 0.13075218 | I25: ='Discount Leakage'!K16 -> 0.12285345 | J25: ='Discount Leakage'!L16 -> 0.0078987282 | K25: ='Discount Leakage'!M16 -> 155.0296 | L25: =$G$7 -> 0.7 | M25: =$G$8 -> 0.99 | N25: =K25*L25*M25 -> 107.43551 | O25: =G25*(1-M25) -> 67.228478 | P25: =N25-O25 -> 40.207036 | Q25: =IF(P25>=100,"Priority",IF(P25>0,"Selective","Do not reprice")) -> Selective
A26: =12 -> 12 | B26: ='Discount Leakage'!B17 -> Northgate Grocers 08 | C26: ='Discount Leakage'!C17 -> Grocery | D26: ='Discount Leakage'!D17 -> Core | E26: ='Discount Leakage'!E17 -> 8306.34 | F26: ='Discount Leakage'!E17*(1-'Discount Leakage'!F17) -> 7043.6544 | G26: =SUMIF('Customer Matrix'!$B$12:$B$101,B26,'Customer Matrix'!$F$12:$F$101) -> 2549.9187 | H26: ='Discount Leakage'!F17 -> 0.15201467 | I26: ='Discount Leakage'!K17 -> 0.13619633 | J26: ='Discount Leakage'!L17 -> 0.015818346 | K26: ='Discount Leakage'!M17 -> 131.39256 | L26: =$G$7 -> 0.7 | M26: =$G$8 -> 0.99 | N26: =K26*L26*M26 -> 91.055044 | O26: =G26*(1-M26) -> 25.499187 | P26: =N26-O26 -> 65.555857 | Q26: =IF(P26>=100,"Priority",IF(P26>0,"Selective","Do not reprice")) -> Selective
A27: =13 -> 13 | B27: ='Discount Leakage'!B18 -> HomeCart Online 01 | C27: ='Discount Leakage'!C18 -> Online Marketplace | D27: ='Discount Leakage'!D18 -> Strategic | E27: ='Discount Leakage'!E18 -> 25879.4 | F27: ='Discount Leakage'!E18*(1-'Discount Leakage'!F18) -> 21393.976 | G27: =SUMIF('Customer Matrix'!$B$12:$B$101,B27,'Customer Matrix'!$F$12:$F$101) -> 7298.4322 | H27: ='Discount Leakage'!F18 -> 0.17332026 | I27: ='Discount Leakage'!K18 -> 0.16836594 | J27: ='Discount Leakage'!L18 -> 0.0049543191 | K27: ='Discount Leakage'!M18 -> 128.2148 | L27: =$G$7 -> 0.7 | M27: =$G$8 -> 0.99 | N27: =K27*L27*M27 -> 88.85286 | O27: =G27*(1-M27) -> 72.984322 | P27: =N27-O27 -> 15.868538 | Q27: =IF(P27>=100,"Priority",IF(P27>0,"Selective","Do not reprice")) -> Selective
A28: =14 -> 14 | B28: ='Discount Leakage'!B19 -> Northgate Grocers 03 | C28: ='Discount Leakage'!C19 -> Grocery | D28: ='Discount Leakage'!D19 -> Strategic | E28: ='Discount Leakage'!E19 -> 21088.41 | F28: ='Discount Leakage'!E19*(1-'Discount Leakage'!F19) -> 17864.194 | G28: =SUMIF('Customer Matrix'!$B$12:$B$101,B28,'Customer Matrix'!$F$12:$F$101) -> 6149.4287 | H28: ='Discount Leakage'!F19 -> 0.15289042 | I28: ='Discount Leakage'!K19 -> 0.14692834 | J28: ='Discount Leakage'!L19 -> 0.0059620826 | K28: ='Discount Leakage'!M19 -> 125.73084 | L28: =$G$7 -> 0.7 | M28: =$G$8 -> 0.99 | N28: =K28*L28*M28 -> 87.131473 | O28: =G28*(1-M28) -> 61.494287 | P28: =N28-O28 -> 25.637186 | Q28: =IF(P28>=100,"Priority",IF(P28>0,"Selective","Do not reprice")) -> Selective
A29: =15 -> 15 | B29: ='Discount Leakage'!B20 -> FamilyCare Wholesale 07 | C29: ='Discount Leakage'!C20 -> Wholesale | D29: ='Discount Leakage'!D20 -> Core | E29: ='Discount Leakage'!E20 -> 7803.73 | F29: ='Discount Leakage'!E20*(1-'Discount Leakage'!F20) -> 6329.2923 | G29: =SUMIF('Customer Matrix'!$B$12:$B$101,B29,'Customer Matrix'!$F$12:$F$101) -> 2042.4329 | H29: ='Discount Leakage'!F20 -> 0.18894013 | I29: ='Discount Leakage'!K20 -> 0.17343 | J29: ='Discount Leakage'!L20 -> 0.015510128 | K29: ='Discount Leakage'!M20 -> 121.03685 | L29: =$G$7 -> 0.7 | M29: =$G$8 -> 0.99 | N29: =K29*L29*M29 -> 83.878536 | O29: =G29*(1-M29) -> 20.424329 | P29: =N29-O29 -> 63.454208 | Q29: =IF(P29>=100,"Priority",IF(P29>0,"Selective","Do not reprice")) -> Selective
A30: =16 -> 16 | B30: ='Discount Leakage'!B21 -> FamilyCare Wholesale 09 | C30: ='Discount Leakage'!C21 -> Wholesale | D30: ='Discount Leakage'!D21 -> Core | E30: ='Discount Leakage'!E21 -> 6556.58 | F30: ='Discount Leakage'!E21*(1-'Discount Leakage'!F21) -> 5297.4714 | G30: =SUMIF('Customer Matrix'!$B$12:$B$101,B30,'Customer Matrix'!$F$12:$F$101) -> 1861.6693 | H30: ='Discount Leakage'!F21 -> 0.19203741 | I30: ='Discount Leakage'!K21 -> 0.1743347 | J30: ='Discount Leakage'!L21 -> 0.01770271 | K30: ='Discount Leakage'!M21 -> 116.06924 | L30: =$G$7 -> 0.7 | M30: =$G$8 -> 0.99 | N30: =K30*L30*M30 -> 80.43598 | O30: =G30*(1-M30) -> 18.616693 | P30: =N30-O30 -> 61.819287 | Q30: =IF(P30>=100,"Priority",IF(P30>0,"Selective","Do not reprice")) -> Selective
A31: =17 -> 17 | B31: ='Discount Leakage'!B22 -> WellSpring Pharmacy 02 | C31: ='Discount Leakage'!C22 -> Pharmacy | D31: ='Discount Leakage'!D22 -> Strategic | E31: ='Discount Leakage'!E22 -> 22395.29 | F31: ='Discount Leakage'!E22*(1-'Discount Leakage'!F22) -> 19566.794 | G31: =SUMIF('Customer Matrix'!$B$12:$B$101,B31,'Customer Matrix'!$F$12:$F$101) -> 7153.0515 | H31: ='Discount Leakage'!F22 -> 0.12629869 | I31: ='Discount Leakage'!K22 -> 0.1212546 | J31: ='Discount Leakage'!L22 -> 0.005044088 | K31: ='Discount Leakage'!M22 -> 112.96381 | L31: =$G$7 -> 0.7 | M31: =$G$8 -> 0.99 | N31: =K31*L31*M31 -> 78.283922 | O31: =G31*(1-M31) -> 71.530515 | P31: =N31-O31 -> 6.7534072 | Q31: =IF(P31>=100,"Priority",IF(P31>0,"Selective","Do not reprice")) -> Selective
A32: =18 -> 18 | B32: ='Discount Leakage'!B23 -> Direct Family Customer 09 | C32: ='Discount Leakage'!C23 -> DTC | D32: ='Discount Leakage'!D23 -> Core | E32: ='Discount Leakage'!E23 -> 6533.78 | F32: ='Discount Leakage'!E23*(1-'Discount Leakage'!F23) -> 6026.3783 | G32: =SUMIF('Customer Matrix'!$B$12:$B$101,B32,'Customer Matrix'!$F$12:$F$101) -> 2480.8113 | H32: ='Discount Leakage'!F23 -> 0.077658215 | I32: ='Discount Leakage'!K23 -> 0.063295703 | J32: ='Discount Leakage'!L23 -> 0.014362512 | K32: ='Discount Leakage'!M23 -> 93.841495 | L32: =$G$7 -> 0.7 | M32: =$G$8 -> 0.99 | N32: =K32*L32*M32 -> 65.032156 | O32: =G32*(1-M32) -> 24.808113 | P32: =N32-O32 -> 40.224043 | Q32: =IF(P32>=100,"Priority",IF(P32>0,"Selective","Do not reprice")) -> Selective
A33: =19 -> 19 | B33: ='Discount Leakage'!B24 -> HomeCart Online 04 | C33: ='Discount Leakage'!C24 -> Online Marketplace | D33: ='Discount Leakage'!D24 -> Core | E33: ='Discount Leakage'!E24 -> 5684.09 | F33: ='Discount Leakage'!E24*(1-'Discount Leakage'!F24) -> 4694.1847 | G33: =SUMIF('Customer Matrix'!$B$12:$B$101,B33,'Customer Matrix'!$F$12:$F$101) -> 1621.4159 | H33: ='Discount Leakage'!F24 -> 0.17415371 | I33: ='Discount Leakage'!K24 -> 0.15894155 | J33: ='Discount Leakage'!L24 -> 0.015212151 | K33: ='Discount Leakage'!M24 -> 86.467235 | L33: =$G$7 -> 0.7 | M33: =$G$8 -> 0.99 | N33: =K33*L33*M33 -> 59.921794 | O33: =G33*(1-M33) -> 16.214159 | P33: =N33-O33 -> 43.707635 | Q33: =IF(P33>=100,"Priority",IF(P33>0,"Selective","Do not reprice")) -> Selective
A34: =20 -> 20 | B34: ='Discount Leakage'!B25 -> Northgate Grocers 04 | C34: ='Discount Leakage'!C25 -> Grocery | D34: ='Discount Leakage'!D25 -> Core | E34: ='Discount Leakage'!E25 -> 9002.95 | F34: ='Discount Leakage'!E25*(1-'Discount Leakage'!F25) -> 7719.0378 | G34: =SUMIF('Customer Matrix'!$B$12:$B$101,B34,'Customer Matrix'!$F$12:$F$101) -> 3083.5951 | H34: ='Discount Leakage'!F25 -> 0.14261017 | I34: ='Discount Leakage'!K25 -> 0.13334897 | J34: ='Discount Leakage'!L25 -> 0.0092611976 | K34: ='Discount Leakage'!M25 -> 83.378099 | L34: =$G$7 -> 0.7 | M34: =$G$8 -> 0.99 | N34: =K34*L34*M34 -> 57.781023 | O34: =G34*(1-M34) -> 30.835951 | P34: =N34-O34 -> 26.945072 | Q34: =IF(P34>=100,"Priority",IF(P34>0,"Selective","Do not reprice")) -> Selective
A37: Scenario summary
A38: Metric | B38: Conservative | C38: Base | D38: Stretch | F38: Selected Scenario KPI | G38: Value | J38: Scenario | K38: Net Contribution Uplift
A39: Recovery % | B39: 0.4 | C39: 0.7 | D39: 0.9 | F39: Scenario | G39: =$B$10 -> Base | J39: Conservative | K39: =B44 -> 1138.0638
A40: Volume Retention % | B40: 0.995 | C40: 0.99 | D40: 0.98 | F40: Top 20 Net Contribution Uplift | G40: =SUM(P15:P34) -> 1833.5756 | J40: Base | K40: =C44 -> 1833.5756
A41: Gross Leakage — Top 20 | B41: =SUM($K$15:$K$34) -> 4296.6219 | C41: =SUM($K$15:$K$34) -> 4296.6219 | D41: =SUM($K$15:$K$34) -> 4296.6219 | F41: Priority Accounts | G41: =COUNTIF(Q15:Q34,"Priority") -> 5 | J41: Stretch | K41: =D44 -> 1501.6538
A42: Price Recapture — Retained Business | B42: =SUM($K$15:$K$34)*B39*B40 -> 1710.0555 | C42: =SUM($K$15:$K$34)*C39*C40 -> 2977.5589 | D42: =SUM($K$15:$K$34)*D39*D40 -> 3789.6205 | F42: Total Potential Recapture — Full Portfolio | G42: ='Discount Leakage'!B102 -> 3875.371
A43: Contribution Lost from Attrition | B43: =SUM($G$15:$G$34)*(1-B40) -> 571.99166 | C43: =SUM($G$15:$G$34)*(1-C40) -> 1143.9833 | D43: =SUM($G$15:$G$34)*(1-D40) -> 2287.9667
A44: Net Contribution Uplift | B44: =B42-B43 -> 1138.0638 | C44: =C42-C43 -> 1833.5756 | D44: =D42-D43 -> 1501.6538

Sheet Customer Action Register
A1: Commercial Customer Action Register
A3: Action register translates the analytical outputs into accountable commercial next steps. Status and owner fields are intentionally editable for portfolio demonstration.
A5: Priority | B5: Customer | C5: Channel | D5: Revenue (£) | E5: Contribution Margin | F5: Discount Rate | G5: Potential Recapture (£) | H5: Customer Quadrant | I5: Recommended Action | J5: Owner | K5: Status | L5: Target Timing | M5: Success Metric | N5: Notes
A6: 1 | B6: ='Discount Leakage'!B6 -> Northgate Grocers 01 | C6: ='Discount Leakage'!C6 -> Grocery | D6: =SUMIF('Customer Matrix'!$B$12:$B$101,B6,'Customer Matrix'!$E$12:$E$101) -> 23314.544 | E6: =SUMIF('Customer Matrix'!$B$12:$B$101,B6,'Customer Matrix'!$G$12:$G$101) -> 0.3531389 | F6: ='Discount Leakage'!F6 -> 0.16467481 | G6: ='Discount Leakage'!O6 -> 383.97994 | H6: =IFERROR(INDEX('Customer Matrix'!$K$12:$K$101,MATCH(B6,'Customer Matrix'!$B$12:$B$101,0)),"") -> Reprice / Cost-to-Serve | I6: =IF(G6>=100,"Reprice / renegotiate",IF(H6="Reprice / Cost-to-Serve","Cost-to-serve review","Monitor / protect")) -> Reprice / renegotiate | J6: Commercial Director | K6: Open | L6: Q4 2026 | M6: Discount within policy and contribution protected | N6: Synthetic portfolio action
A7: 2 | B7: ='Discount Leakage'!B7 -> FamilyCare Wholesale 01 | C7: ='Discount Leakage'!C7 -> Wholesale | D7: =SUMIF('Customer Matrix'!$B$12:$B$101,B7,'Customer Matrix'!$E$12:$E$101) -> 16715.165 | E7: =SUMIF('Customer Matrix'!$B$12:$B$101,B7,'Customer Matrix'!$G$12:$G$101) -> 0.33949155 | F7: ='Discount Leakage'!F7 -> 0.2090308 | G7: ='Discount Leakage'!O7 -> 339.88501 | H7: =IFERROR(INDEX('Customer Matrix'!$K$12:$K$101,MATCH(B7,'Customer Matrix'!$B$12:$B$101,0)),"") -> Reprice / Cost-to-Serve | I7: =IF(G7>=100,"Reprice / renegotiate",IF(H7="Reprice / Cost-to-Serve","Cost-to-serve review","Monitor / protect")) -> Reprice / renegotiate | J7: Key Account Manager | K7: In progress | L7: Q4 2026 | M7: Discount within policy and contribution protected | N7: Synthetic portfolio action
A8: 3 | B8: ='Discount Leakage'!B8 -> FamilyCare Wholesale 03 | C8: ='Discount Leakage'!C8 -> Wholesale | D8: =SUMIF('Customer Matrix'!$B$12:$B$101,B8,'Customer Matrix'!$E$12:$E$101) -> 17977.78 | E8: =SUMIF('Customer Matrix'!$B$12:$B$101,B8,'Customer Matrix'!$G$12:$G$101) -> 0.33092259 | F8: ='Discount Leakage'!F8 -> 0.1993856 | G8: ='Discount Leakage'!O8 -> 282.57018 | H8: =IFERROR(INDEX('Customer Matrix'!$K$12:$K$101,MATCH(B8,'Customer Matrix'!$B$12:$B$101,0)),"") -> Reprice / Cost-to-Serve | I8: =IF(G8>=100,"Reprice / renegotiate",IF(H8="Reprice / Cost-to-Serve","Cost-to-serve review","Monitor / protect")) -> Reprice / renegotiate | J8: Finance Business Partner | K8: Open | L8: Q4 2026 | M8: Discount within policy and contribution protected | N8: Synthetic portfolio action
A9: 4 | B9: ='Discount Leakage'!B9 -> HomeCart Online 03 | C9: ='Discount Leakage'!C9 -> Online Marketplace | D9: =SUMIF('Customer Matrix'!$B$12:$B$101,B9,'Customer Matrix'!$E$12:$E$101) -> 21060.262 | E9: =SUMIF('Customer Matrix'!$B$12:$B$101,B9,'Customer Matrix'!$G$12:$G$101) -> 0.31575939 | F9: ='Discount Leakage'!F9 -> 0.179612 | G9: ='Discount Leakage'!O9 -> 256.08718 | H9: =IFERROR(INDEX('Customer Matrix'!$K$12:$K$101,MATCH(B9,'Customer Matrix'!$B$12:$B$101,0)),"") -> Reprice / Cost-to-Serve | I9: =IF(G9>=100,"Reprice / renegotiate",IF(H9="Reprice / Cost-to-Serve","Cost-to-serve review","Monitor / protect")) -> Reprice / renegotiate | J9: Pricing Manager | K9: Monitoring | L9: Q4 2026 | M9: Discount within policy and contribution protected | N9: Synthetic portfolio action
A10: 5 | B10: ='Discount Leakage'!B10 -> Direct Family Customer 02 | C10: ='Discount Leakage'!C10 -> DTC | D10: =SUMIF('Customer Matrix'!$B$12:$B$101,B10,'Customer Matrix'!$E$12:$E$101) -> 28448.002 | E10: =SUMIF('Customer Matrix'!$B$12:$B$101,B10,'Customer Matrix'!$G$12:$G$101) -> 0.37798374 | F10: ='Discount Leakage'!F10 -> 0.081698949 | G10: ='Discount Leakage'!O10 -> 212.70422 | H10: =IFERROR(INDEX('Customer Matrix'!$K$12:$K$101,MATCH(B10,'Customer Matrix'!$B$12:$B$101,0)),"") -> Protect / Grow | I10: =IF(G10>=100,"Reprice / renegotiate",IF(H10="Reprice / Cost-to-Serve","Cost-to-serve review","Monitor / protect")) -> Reprice / renegotiate | J10: Commercial Director | K10: Open | L10: Q4 2026 | M10: Discount within policy and contribution protected | N10: Synthetic portfolio action
A11: 6 | B11: ='Discount Leakage'!B11 -> WellSpring Pharmacy 03 | C11: ='Discount Leakage'!C11 -> Pharmacy | D11: =SUMIF('Customer Matrix'!$B$12:$B$101,B11,'Customer Matrix'!$E$12:$E$101) -> 20045.679 | E11: =SUMIF('Customer Matrix'!$B$12:$B$101,B11,'Customer Matrix'!$G$12:$G$101) -> 0.38243352 | F11: ='Discount Leakage'!F11 -> 0.13566147 | G11: ='Discount Leakage'!O11 -> 173.37141 | H11: =IFERROR(INDEX('Customer Matrix'!$K$12:$K$101,MATCH(B11,'Customer Matrix'!$B$12:$B$101,0)),"") -> Protect / Grow | I11: =IF(G11>=100,"Reprice / renegotiate",IF(H11="Reprice / Cost-to-Serve","Cost-to-serve review","Monitor / protect")) -> Reprice / renegotiate | J11: Key Account Manager | K11: In progress | L11: Q4 2026 | M11: Discount within policy and contribution protected | N11: Synthetic portfolio action
A12: 7 | B12: ='Discount Leakage'!B12 -> LittleNest Retail 02 | C12: ='Discount Leakage'!C12 -> Baby Specialist | D12: =SUMIF('Customer Matrix'!$B$12:$B$101,B12,'Customer Matrix'!$E$12:$E$101) -> 23824.362 | E12: =SUMIF('Customer Matrix'!$B$12:$B$101,B12,'Customer Matrix'!$G$12:$G$101) -> 0.36921248 | F12: ='Discount Leakage'!F12 -> 0.12358106 | G12: ='Discount Leakage'!O12 -> 163.95908 | H12: =IFERROR(INDEX('Customer Matrix'!$K$12:$K$101,MATCH(B12,'Customer Matrix'!$B$12:$B$101,0)),"") -> Reprice / Cost-to-Serve | I12: =IF(G12>=100,"Reprice / renegotiate",IF(H12="Reprice / Cost-to-Serve","Cost-to-serve review","Monitor / protect")) -> Reprice / renegotiate | J12: Finance Business Partner | K12: Open | L12: Q4 2026 | M12: Discount within policy and contribution protected | N12: Synthetic portfolio action
A13: 8 | B13: ='Discount Leakage'!B13 -> HomeCart Online 02 | C13: ='Discount Leakage'!C13 -> Online Marketplace | D13: =SUMIF('Customer Matrix'!$B$12:$B$101,B13,'Customer Matrix'!$E$12:$E$101) -> 20627.807 | E13: =SUMIF('Customer Matrix'!$B$12:$B$101,B13,'Customer Matrix'!$G$12:$G$101) -> 0.33133209 | F13: ='Discount Leakage'!F13 -> 0.17193183 | G13: ='Discount Leakage'!O13 -> 144.53471 | H13: =IFERROR(INDEX('Customer Matrix'!$K$12:$K$101,MATCH(B13,'Customer Matrix'!$B$12:$B$101,0)),"") -> Reprice / Cost-to-Serve | I13: =IF(G13>=100,"Reprice / renegotiate",IF(H13="Reprice / Cost-to-Serve","Cost-to-serve review","Monitor / protect")) -> Reprice / renegotiate | J13: Pricing Manager | K13: Monitoring | L13: Q4 2026 | M13: Discount within policy and contribution protected | N13: Synthetic portfolio action
A14: 9 | B14: ='Discount Leakage'!B14 -> FamilyCare Wholesale 02 | C14: ='Discount Leakage'!C14 -> Wholesale | D14: =SUMIF('Customer Matrix'!$B$12:$B$101,B14,'Customer Matrix'!$E$12:$E$101) -> 15578.153 | E14: =SUMIF('Customer Matrix'!$B$12:$B$101,B14,'Customer Matrix'!$G$12:$G$101) -> 0.30827919 | F14: ='Discount Leakage'!F14 -> 0.19087436 | G14: ='Discount Leakage'!O14 -> 127.50924 | H14: =IFERROR(INDEX('Customer Matrix'!$K$12:$K$101,MATCH(B14,'Customer Matrix'!$B$12:$B$101,0)),"") -> Reprice / Cost-to-Serve | I14: =IF(G14>=100,"Reprice / renegotiate",IF(H14="Reprice / Cost-to-Serve","Cost-to-serve review","Monitor / protect")) -> Reprice / renegotiate | J14: Commercial Director | K14: Open | L14: Q4 2026 | M14: Discount within policy and contribution protected | N14: Synthetic portfolio action
A15: 10 | B15: ='Discount Leakage'!B15 -> Direct Family Customer 03 | C15: ='Discount Leakage'!C15 -> DTC | D15: =SUMIF('Customer Matrix'!$B$12:$B$101,B15,'Customer Matrix'!$E$12:$E$101) -> 20694.212 | E15: =SUMIF('Customer Matrix'!$B$12:$B$101,B15,'Customer Matrix'!$G$12:$G$101) -> 0.39021647 | F15: ='Discount Leakage'!F15 -> 0.083759327 | G15: ='Discount Leakage'!O15 -> 115.14717 | H15: =IFERROR(INDEX('Customer Matrix'!$K$12:$K$101,MATCH(B15,'Customer Matrix'!$B$12:$B$101,0)),"") -> Protect / Grow | I15: =IF(G15>=100,"Reprice / renegotiate",IF(H15="Reprice / Cost-to-Serve","Cost-to-serve review","Monitor / protect")) -> Reprice / renegotiate | J15: Key Account Manager | K15: In progress | L15: Q4 2026 | M15: Discount within policy and contribution protected | N15: Synthetic portfolio action
A16: 11 | B16: ='Discount Leakage'!B16 -> WellSpring Pharmacy 01 | C16: ='Discount Leakage'!C16 -> Pharmacy | D16: =SUMIF('Customer Matrix'!$B$12:$B$101,B16,'Customer Matrix'!$E$12:$E$101) -> 17060.866 | E16: =SUMIF('Customer Matrix'!$B$12:$B$101,B16,'Customer Matrix'!$G$12:$G$101) -> 0.3940508 | F16: ='Discount Leakage'!F16 -> 0.13075218 | G16: ='Discount Leakage'!O16 -> 108.52072 | H16: =IFERROR(INDEX('Customer Matrix'!$K$12:$K$101,MATCH(B16,'Customer Matrix'!$B$12:$B$101,0)),"") -> Protect / Grow | I16: =IF(G16>=100,"Reprice / renegotiate",IF(H16="Reprice / Cost-to-Serve","Cost-to-serve review","Monitor / protect")) -> Reprice / renegotiate | J16: Finance Business Partner | K16: Open | L16: Q1 2027 | M16: Discount within policy and contribution protected | N16: Synthetic portfolio action
A17: 12 | B17: ='Discount Leakage'!B17 -> Northgate Grocers 08 | C17: ='Discount Leakage'!C17 -> Grocery | D17: =SUMIF('Customer Matrix'!$B$12:$B$101,B17,'Customer Matrix'!$E$12:$E$101) -> 7043.6544 | E17: =SUMIF('Customer Matrix'!$B$12:$B$101,B17,'Customer Matrix'!$G$12:$G$101) -> 0.36201643 | F17: ='Discount Leakage'!F17 -> 0.15201467 | G17: ='Discount Leakage'!O17 -> 91.974791 | H17: =IFERROR(INDEX('Customer Matrix'!$K$12:$K$101,MATCH(B17,'Customer Matrix'!$B$12:$B$101,0)),"") -> Reprice / Cost-to-Serve | I17: =IF(G17>=100,"Reprice / renegotiate",IF(H17="Reprice / Cost-to-Serve","Cost-to-serve review","Monitor / protect")) -> Cost-to-serve review | J17: Pricing Manager | K17: Monitoring | L17: Q1 2027 | M17: Discount within policy and contribution protected | N17: Synthetic portfolio action
... A25: 20 | B25: ='Discount Leakage'!B25 -> Northgate Grocers 04 | C25: ='Discount Leakage'!C25 -> Grocery | D25: =SUMIF('Customer Matrix'!$B$12:$B$101,B25,'Customer Matrix'!$E$12:$E$101) -> 7719.0378 | E25: =SUMIF('Customer Matrix'!$B$12:$B$101,B25,'Customer Matrix'!$G$12:$G$101) -> 0.39947921 | F25: ='Discount Leakage'!F25 -> 0.14261017 | G25: ='Discount Leakage'!O25 -> 58.36467 | H25: =IFERROR(INDEX('Customer Matrix'!$K$12:$K$101,MATCH(B25,'Customer Matrix'!$B$12:$B$101,0)),"") -> Protect / Grow | I25: =IF(G25>=100,"Reprice / renegotiate",IF(H25="Reprice / Cost-to-Serve","Cost-to-serve review","Monitor / protect")) -> Monitor / protect | J25: Pricing Manager | K25: Monitoring | L25: Q1 2027 | M25: Discount within policy and contribution protected | N25: Synthetic portfolio action
A28: Action register summary
A29: Metric | B29: Value | C29: Meaning | D29: Source
A30: Open Actions | B30: =COUNTIF(K6:K25,"Open") -> 10 | C30: Actions requiring follow-up | D30: Register
A31: In-Progress Actions | B31: =COUNTIF(K6:K25,"In progress") -> 5 | C31: Actions currently being progressed | D31: Register
A32: Priority Repricing Value | B32: =SUM(G6:G25) -> 3007.6353 | C32: Modelled recapture attached to top actions | D32: Discount Leakage
A33: High-Revenue / Low-Margin Accounts | B33: =COUNTIF(H6:H25,"Reprice / Cost-to-Serve") -> 12 | C33: Customer quadrant requiring economics review | D33: Customer Matrix
A34: Actions Due Q4 2026 | B34: =COUNTIF(L6:L25,"Q4 2026") -> 10 | C34: Near-term commercial agenda | D34: Register

Sheet Commercial Commentary
A1: Automated Commercial Finance Commentary
A3: ="Scenario: "&'Pricing Scenarios'!B10&" | Commentary refreshes from model outputs" -> Scenario: Base | Commentary refreshes from model outputs
A5: Executive performance
A6: ="The commercial portfolio generated £"&ROUND(SUM('Fact Sales'!M4:M2003)/1000,1)&"k net revenue at "&ROUND(SUM('Fact Sales'!U4:U2003)/SUM('Fact Sales'!M4:M2003)*100,1)&"% contribution margin. "&IF('Pricing Scenarios'!G40>=0,"The "&'Pricing Scenarios'!B10&" repricing scenario identifies £"&ROUND('Pricing Scenarios'!G40,0)&" of risk-adjusted contribution upside across the top 20 opportunities.","The "&'Pricing Scenarios'!B10&" repricing scenario is value-destructive by £"&ROUND(-'Pricing Scenarios'!G40,0)&", indicating that expected attrition outweighs price recovery.") -> The commercial portfolio generated £632.8k net revenue at 36.5% contribution margin. The Base repricing scenario identifies £1834 of risk-adjusted contribution upside across the top 20 opportunities.
A10: Pricing & discount governance
A11: ="Modelled gross discount leakage is £"&ROUND('Discount Leakage'!B101,0)&" and full-portfolio potential recapture is £"&ROUND('Discount Leakage'!B102,0)&". "&ROUND('Discount Leakage'!B103,0)&" accounts are classified as priority repricing opportunities under the original leakage screen." -> Modelled gross discount leakage is £5536 and full-portfolio potential recapture is £3875. 11 accounts are classified as priority repricing opportunities under the original leakage screen.
A15: Customer economics
A16: ="The top 10 customers represent "&ROUND('Customer Concentration'!B9*100,1)&"% of revenue. "&ROUND('Customer Action Register'!B33,0)&" of the top action-list accounts fall into the high-revenue / low-margin customer quadrant, "&"where discount and cost-to-serve should be reviewed before pursuing further volume." -> The top 10 customers represent 36.2% of revenue. 12 of the top action-list accounts fall into the high-revenue / low-margin customer quadrant, where discount and cost-to-serve should be reviewed before pursuing further volume.
A20: Promotion effectiveness
A21: ="Promotion analysis is deliberately treated as an observational proxy rather than causal evidence. "&COUNTIF('Promo Effectiveness'!M7:M12,"Value destructive")&" categories show negative ROI proxies and should be redesigned or tested before additional spend is committed." -> Promotion analysis is deliberately treated as an observational proxy rather than causal evidence. 4 categories show negative ROI proxies and should be redesigned or tested before additional spend is committed.
A25: Portfolio & growth bridge
A26: ="Jan–Sep 2026 net revenue is £"&ROUND('PVM Analysis V2'!L12,0)&" above the prior-year period. "&"Volume is "&IF('PVM Analysis V2'!H12>=0,"£"&ROUND('PVM Analysis V2'!H12,0)&" favourable","£"&ROUND(-'PVM Analysis V2'!H12,0)&" adverse")&", mix is "&IF('PVM Analysis V2'!I12>=0,"£"&ROUND('PVM Analysis V2'!I12,0)&" favourable","£"&ROUND(-'PVM Analysis V2'!I12,0)&" adverse")&" and price is "&IF('PVM Analysis V2'!J12>=0,"£"&ROUND('PVM Analysis V2'!J12,0)&" favourable","£"&ROUND(-'PVM Analysis V2'!J12,0)&" adverse")&". SKU actions should protect price realisation while addressing weak portfolio mix and low-margin tail." -> Jan–Sep 2026 net revenue is £17545 above the prior-year period. Volume is £8337 favourable, mix is £2227 adverse and price is £11435 favourable. SKU actions should protect price realisation while addressing weak portfolio mix and low-margin tail.
A31: Commercial Finance priorities
A32: Priority | B32: Focus Area | C32: Evidence | D32: Owner | E32: Recommended Action | F32: Status
A33: 1 | B33: Repricing | C33: Excess discount vs policy | D33: Pricing Manager | E33: Progress top risk-adjusted repricing cases | F33: Open
A34: 2 | B34: Customer economics | C34: High revenue / low margin | D34: Finance Business Partner | E34: Review discount, freight and service economics | F34: In progress
A35: 3 | B35: Promotions | C35: Negative ROI proxy | D35: Commercial Director | E35: Redesign or test low-return promotions | F35: Open
A36: 4 | B36: SKU portfolio | C36: Low revenue / low margin tail | D36: Commercial Director | E36: Review delisting / simplification candidates | F36: Monitoring
A37: 5 | B37: Growth mix | C37: Negative category mix effect | D37: Finance Business Partner | E37: Protect profitable mix while scaling volume | F37: In progress

Sheet Commercial Management Pack
A1: Lumina Baby & Family Care Ltd — Commercial Finance Management Pack
A3: ="Commercial outlook | Repricing scenario: "&'Pricing Scenarios'!B10&" | Synthetic portfolio case study" -> Commercial outlook | Repricing scenario: Base | Synthetic portfolio case study
A5: Net Revenue | D5: Contribution Profit | G5: Contribution Margin | J5: Risk-Adjusted Repricing Uplift
A6: =Dashboard!A6 -> £632,781 | D6: =Dashboard!J6 -> £231,064 | G6: =Dashboard!A10 -> 36.5% | J6: ='Pricing Scenarios'!G40 -> 1833.5756
A10: Executive summary
A11: ='Commercial Commentary'!A6&CHAR(10)&CHAR(10)&'Commercial Commentary'!A11&CHAR(10)&CHAR(10)&'Commercial Commentary'!A16 -> The commercial portfolio generated £632.8k net revenue at 36.5% contribution margin. The Base repricing scenario identifies £1834 of risk-adjusted contribution upside across the top 20 opportunities. Modelled gross discount leakage is £5536 and full-portfolio potential recapture is £3875. 11 accounts are classified as priority repricing opportunities under the original leakage screen. The top 10 customers represent 36.2% of revenue. 12 of the top action-list accounts fall into the high-revenue / low-margin customer quadrant, where discount and cost-to-serve should be reviewed before pursuing further volume.
A18: Pricing & customer economics | H18: Jan–Sep revenue growth bridge
A19: Metric | B19: Value | C19: Comparator / Rule | D19: Management Interpretation | H19: Driver | I19: Effect (£)
A20: Gross Discount Leakage | B20: ='Discount Leakage'!B101 -> 5536.2442 | C20: Above synthetic policy | D20: Pricing governance gap | H20: Volume | I20: ='PVM Analysis V2'!H12 -> 8336.8424
A21: Full-Portfolio Potential Recapture | B21: ='Discount Leakage'!B102 -> 3875.371 | C21: 70% original realisation assumption | D21: Opportunity screen | H21: Mix | I21: ='PVM Analysis V2'!I12 -> -2227.183
A22: Top 20 Risk-Adjusted Uplift | B22: ='Pricing Scenarios'!G40 -> 1833.5756 | C22: Selected repricing scenario | D22: Contribution impact after retention risk | H22: Price | I22: ='PVM Analysis V2'!J12 -> 11435.062
A23: Top 10 Customer Share | B23: ='Customer Concentration'!B9 -> 0.36180563 | C23: Portfolio concentration | D23: Customer dependency | H23: Net Change | I23: ='PVM Analysis V2'!L12 -> 17544.722
A24: High Revenue / Low Margin Actions | B24: ='Customer Action Register'!B33 -> 12 | C24: Quadrant screen | D24: Needs economics review
A28: Promotion & SKU portfolio
A29: Metric | B29: Value | C29: Signal | D29: Action
A30: Value-Destructive Promo Categories | B30: =COUNTIF('Promo Effectiveness'!M7:M12,"Value destructive") -> 4 | C30: Negative ROI proxy | D30: Redesign / retest
A31: Strong Promo Categories | B31: =COUNTIF('Promo Effectiveness'!M7:M12,"Strong") -> 1 | C31: ROI proxy ≥ 1.0x | D31: Scale carefully / validate
A32: Protect / Grow SKUs | B32: ='SKU Rationalisation'!B64 -> 11 | C32: High revenue / high margin | D32: Defend and expand
A33: Reprice / Cost Action SKUs | B33: ='SKU Rationalisation'!B65 -> 13 | C33: High revenue / low margin | D33: Price/cost intervention
A34: Rationalise / Review SKUs | B34: ='SKU Rationalisation'!B67 -> 11 | C34: Low revenue / low margin | D34: Simplification review | H34: Selected repricing scenarios
A35: Customer Actions Due Q4 | B35: ='Customer Action Register'!B34 -> 10 | C35: Near-term priorities | D35: Commercial cadence | H35: Metric | I35: Conservative | J35: Base | K35: Stretch
H36: Recovery % | I36: 0.4 | J36: 0.7 | K36: 0.9
H37: Retention % | I37: 0.995 | J37: 0.99 | K37: 0.98
H38: Net Contribution Uplift | I38: ='Pricing Scenarios'!B44 -> 1138.0638 | J38: ='Pricing Scenarios'!C44 -> 1833.5756 | K38: ='Pricing Scenarios'!D44 -> 1501.6538
H39: Selected? | I39: =IF('Pricing Scenarios'!B10="Conservative","✓","") | J39: =IF('Pricing Scenarios'!B10="Base","✓","") -> ✓ | K39: =IF('Pricing Scenarios'!B10="Stretch","✓","")
A42: CFO / Commercial Director priority actions | H42: Management commentary
A43: Priority | B43: Action | C43: Owner | D43: Timing | E43: Evidence | F43: Status | H43: ='Commercial Commentary'!A21&CHAR(10)&CHAR(10)&'Commercial Commentary'!A26 -> Promotion analysis is deliberately treated as an observational proxy rather than causal evidence. 4 categories show negative ROI proxies and should be redesigned or tested before additional spend is committed. Jan–Sep 2026 net revenue is £17545 above the prior-year period. Volume is £8337 favourable, mix is £2227 adverse and price is £11435 favourable. SKU actions should protect price realisation while addressing weak portfolio mix and low-margin tail.
A44: 1 | B44: Progress highest risk-adjusted repricing cases | C44: Pricing / Commercial | D44: Q4 | E44: Pricing scenario model | F44: Open
A45: 2 | B45: Review high-revenue / low-margin customer economics | C45: Finance / KAM | D45: Q4 | E45: Customer matrix | F45: In progress
A46: 3 | B46: Redesign negative-ROI promotion mechanics | C46: Commercial / Marketing | D46: Q4 | E46: Promo effectiveness | F46: Open
A47: 4 | B47: Review low-revenue / low-margin SKU tail | C47: Commercial / Supply | D47: Q1 | E47: SKU rationalisation | F47: Monitoring
A48: 5 | B48: Protect price realisation while improving portfolio mix | C48: Finance / Commercial | D48: Q4–Q1 | E48: PVM bridge | F48: In progress

Sheet Power BI Build Spec
A1: Power BI Build Specification — Commercial Finance
A3: This sheet defines the model and measures required for a Power BI implementation. It does not claim that a PBIX file has been produced in this workbook build.
A6: Star schema relationships
A7: From Table | B7: From Key | C7: To Table | D7: To Key | E7: Cardinality | F7: Filter Direction
A8: Dim Date | B8: Date | C8: Fact Sales | D8: Date | E8: 1:* | F8: Single
A9: Dim Customer | B9: Customer_ID | C9: Fact Sales | D9: Customer_ID | E9: 1:* | F9: Single
A10: Dim Product | B10: Product_ID | C10: Fact Sales | D10: Product_ID | E10: 1:* | F10: Single
A11: — | B11: — | C11: — | D11: — | E11: — | F11: Avoid fact-to-fact relationships
A14: Core DAX measures
A15: Measure | B15: DAX | C15: Format | D15: Purpose
A16: Net Revenue | B16: Net Revenue = SUM(FactSales[Net_Revenue]) | C16: £#,##0 | D16: Commercial revenue
A17: Gross Sales | B17: Gross Sales = SUM(FactSales[Gross_Sales]) | C17: £#,##0 | D17: Pre-discount sales
A18: Discount Value | B18: Discount Value = SUM(FactSales[Discount_Value]) | C18: £#,##0 | D18: Discount concession
A19: Discount Rate % | B19: Discount Rate % = DIVIDE([Discount Value],[Gross Sales]) | C19: 0.0% | D19: Pricing governance
A20: Gross Profit | B20: Gross Profit = SUM(FactSales[Gross_Profit]) | C20: £#,##0 | D20: Gross profit
A21: Gross Margin % | B21: Gross Margin % = DIVIDE([Gross Profit],[Net Revenue]) | C21: 0.0% | D21: Gross margin
A22: Contribution Profit | B22: Contribution Profit = SUM(FactSales[Contribution_Profit]) | C22: £#,##0 | D22: Commercial contribution
A23: Contribution Margin % | B23: Contribution Margin % = DIVIDE([Contribution Profit],[Net Revenue]) | C23: 0.0% | D23: Commercial margin
A24: Units | B24: Units = SUM(FactSales[Units]) | C24: #,##0 | D24: Volume
A25: ASP | B25: ASP = DIVIDE([Net Revenue],[Units]) | C25: £0.00 | D25: Realised selling price
A26: Promo Spend | B26: Promo Spend = SUM(FactSales[Promo_Spend]) | C26: £#,##0 | D26: Promotional investment
... A29: Revenue YoY % | B29: Revenue YoY % = DIVIDE([Net Revenue]-[Revenue LY],[Revenue LY]) | C29: 0.0% | D29: Growth
A32: Recommended report pages
A33: Page | B33: Business Question | C33: Key Visuals | D33: Primary Filters | E33: Decision Use
A34: 1. Executive Commercial | B34: How is the portfolio performing? | C34: KPI cards; revenue/margin trend; channel contribution | D34: Date; Channel | E34: Weekly / monthly commercial review
A35: 2. Customer Economics | B35: Which accounts create value? | C35: Revenue vs margin matrix; top customers; discount table | D35: Channel; Tier; Customer | E35: Pricing and account planning
A36: 3. Pricing & Discounts | B36: Where is pricing leaking? | C36: Discount waterfall; leakage ranking; effective discount by account | D36: Channel; Tier | E36: Repricing actions
A37: 4. Product / SKU | B37: Which products should we grow, reprice or rationalise? | C37: SKU quadrant; category margin; contribution waterfall | D37: Brand; Category | E37: Portfolio decisions
A38: 5. Promotions | B38: Are promotions creating economic value? | C38: Promo/non-promo comparison; ROI proxy; volume uplift | D38: Category; Promo Flag | E38: Promo design / testing

Sheet Portfolio Summary
A3: Lumina Baby & Family Care Ltd | Independent synthetic FMCG case study | Final portfolio release
A5: Project objective
A6: Built an end-to-end Commercial Finance case study for a simulated UK FMCG business, using transaction-level sales data to analyse pricing, discount leakage, customer and SKU profitability, promotion economics, customer concentration and Price–Volume–Mix. Extended the analysis into scenario-based repricing, commercial actions and an executive management pack.
A11: Portfolio scope | H11: Key model outputs
A12: Dataset | B12: 2,000 synthetic sales transaction lines | H12: Net Revenue | I12: ='Commercial Management Pack'!A6 -> £632,781 | J12: £000
A13: Customers | B13: 90 customer accounts across 6 channels | H13: Contribution Profit | I13: ='Commercial Management Pack'!D6 -> £231,064 | J13: £000
A14: SKUs | B14: 48 products across 6 categories and 4 brands | H14: Contribution Margin | I14: ='Commercial Management Pack'!G6 -> 36.5% | J14: %
A15: Period | B15: Jan-2025 to Sep-2026 | H15: Gross Discount Leakage | I15: ='Discount Leakage'!B101 -> 5536.2442 | J15: £
A16: Finance focus | B16: Pricing, margin, customer profitability and commercial decision support | H16: Potential Recapture | I16: ='Discount Leakage'!B102 -> 3875.371 | J16: £
A17: Database | B17: SQLite with reusable SQL analysis queries | H17: Base Risk-Adjusted Repricing Uplift | I17: ='Pricing Scenarios'!G40 -> 1833.5756 | J17: £
A18: Excel | B18: Commercial modelling, scenario analysis, dashboards and management pack | H18: Top 10 Customer Revenue Share | I18: ='Customer Concentration'!B9 -> 0.36180563 | J18: %
A19: Power BI | B19: Star-schema + DAX build specification; no PBIX claimed | H19: YTD Revenue Change | I19: ='PVM Analysis V2'!L12 -> 17544.722 | J19: £
A22: Key analytical findings
A23: Pricing governance | B23: ~£5.5k gross discount leakage and ~£3.9k potential recapture under the original 70% realisation screen.
A24: Risk-adjusted repricing | B24: Base scenario produces ~£1.8k net contribution uplift across the top 20 opportunities after allowing for 99% volume retention.
A25: Customer economics | B25: Top 10 customers represent ~36.2% of revenue; 12 top action-list accounts sit in the high-revenue / low-margin quadrant.
A26: Growth drivers | B26: Jan–Sep 2026 revenue is ~£17.5k above prior year: ~£8.3k favourable volume, ~£2.2k adverse mix and ~£11.4k favourable price.
A27: Promotion economics | B27: Four of six categories show negative observational promo ROI proxies; these are screening signals, not causal proof.
A28: SKU portfolio | B28: 13 SKUs are Reprice / Cost Action and 11 are Rationalise / Review.
A31: Core capabilities demonstrated | H31: Tool implementation status
A32: Commercial Finance | B32: Customer and product economics beyond revenue reporting | H32: Tool | I32: Status | J32: Evidence
A33: Pricing | B33: Discount governance, repricing scenarios and retention-risk trade-offs | H33: Microsoft Excel | I33: Implemented | J33: Financial modelling, scenarios, dashboards, management reporting
A34: Profitability | B34: Gross margin, contribution margin and cost-to-serve | H34: SQL / SQLite | I34: Implemented | J34: Database + reusable analysis queries in package
A35: SQL | B35: SQLite queries for channel, customer, SKU, discount and trend analysis | H35: Power BI / DAX | I35: Specified, not PBIX | J35: Star schema, DAX library and report-page specification
A36: Data Modelling | B36: Date / Customer / Product dimensions with transaction fact table | H36: Synthetic data | I36: Explicitly labelled | J36: No confidential or real-employer data used
A37: PVM | B37: Like-for-like Price–Volume–Mix decomposition
A38: Promotion Analysis | B38: Promo vs non-promo economics and observational ROI proxy
A39: Business Partnering | B39: Customer actions, owners, timing, commentary and management pack
A42: Recruiter-safe project description
A43: Independent Commercial Finance case study for a simulated UK FMCG company. Built a transaction-level profitability model and SQLite analysis workflow covering customer, product, channel and promotional economics. Developed discount-leakage diagnostics, customer and SKU portfolio matrices, Price–Volume–Mix analysis, risk-adjusted repricing scenarios and a Commercial Finance management pack. All financial data is synthetic; modelled opportunities are planning scenarios rather than realised savings.
A50: How to review
A51: Recommended review order: 1. Portfolio Summary 2. Commercial Management Pack 3. Pricing Scenarios + Discount Leakage 4. Customer Matrix + Customer Action Register 5. Promo Effectiveness + SKU Rationalisation 6. PVM Analysis V2 7. Power BI Build Spec and SQL files in the release package
